{
    "Experiment": {
        "Leg Guardian Pet": {
            "locked": false,
            "xpRequired": 150000,
            "f": 0.3,
            "image": "guardian.png"
        },
        "A Beginner's Guide to Pesthunting": {
            "locked": false,
            "xpRequired": 500000,
            "image": "guide.png"
        },
        "Severed Pincer": {
            "locked": false,
            "xpRequired": 500000
        },
        "Ensnared Snail": {
            "locked": false,
            "xpRequired": 500000
        },
        "Golden Bounty": {
            "locked": false,
            "xpRequired": 500000
        },
        "Gold Bottle Cap": {
            "locked": false,
            "xpRequired": 500000
        },
        "Chain of the End Times": {
            "locked": false,
            "xpRequired": 500000
        },
        "Octopus Tendril": {
            "locked": false,
            "xpRequired": 500000
        },
        "Troubled Bubble": {
            "locked": false,
            "xpRequired": 500000
        },
        "Severed Hand": {
            "locked": false,
            "xpRequired": 500000
        },
        "End Stone Idol": {
            "locked": false,
            "xpRequired": 500000
        },
        "T7 Books": {
            "locked": false,
            "xpRequired": 500000,
            "image": "enchanted_book.gif"
        },
        "Nadeshiko Dye": {
            "dye": true,
            "locked": false,
            "xpRequired": 2500000,
            "f": 5
        }
    },
    "Zombie": {
        "Matcha Dye": {
            "dye": true,
            "table": "Handled Separately",
            "locked": false,
            "xpRequired": 75000000,
            "w4": 0.0002,
            "w5": 0.0004,
            "r": "None"
        },
        "Foul Flesh": {
            "locked": false,
            "xpRequired": 3093,
            "w4": 2000,
            "w5": 2000,
            "am4": 2.5,
            "am5": 3.5,
            "table": "Main",
            "r": "None"
        },
        "Revenant Shard": {
            "locked": false,
            "xpRequired": 36867,
            "w4": 200,
            "w5": 200,
            "table": "Main",
            "r": "None"
        },
        "◆ Pestilence Rune I": {
            "locked": false,
            "xpRequired": 8007,
            "w4": 833,
            "w5": 833,
            "table": "Extra",
            "image": "pestilence_rune.png",
            "r": "Slayer Lv.2"
        },
        "Undead Catalyst": {
            "locked": false,
            "xpRequired": 24750,
            "w4": 75,
            "w5": 250,
            "table": "Main",
            "r": "Slayer Lv.3"
        },
        "Smite VI": {
            "locked": false,
            "xpRequired": 62434,
            "w4": 100,
            "w5": 100,
            "table": "Main",
            "image": "enchanted_book.gif",
            "r": "Slayer Lv.4"
        },
        "Beheaded Horror": {
            "locked": false,
            "xpRequired": 312175,
            "w4": 20,
            "w5": 20,
            "table": "Main",
            "r": "Slayer Lv.5"
        },
        "Revenant Catalyst": {
            "locked": false,
            "xpRequired": 49500,
            "w4": 125,
            "w5": 125,
            "table": "Main",
            "r": "Slayer Lv.6"
        },
        "◆ Snake Rune I": {
            "locked": false,
            "xpRequired": 333500,
            "w4": 20,
            "w5": 20,
            "table": "Extra",
            "image": "snake_rune.png",
            "r": "Slayer Lv.6"
        },
        "Festering Maggot": {
            "locked": false,
            "xpRequired": 368674,
            "w4": 20,
            "w5": 20,
            "table": "Main",
            "r": "Slayer Lv.6"
        },
        "Scythe Blade": {
            "locked": false,
            "xpRequired": 491566,
            "w4": 7,
            "w5": 15,
            "table": "Main",
            "image": "enchanted_diamond.gif",
            "r": "Slayer Lv.7"
        },
        "Revenant Viscera": {
            "locked": false,
            "xpRequired": 3686,
            "w5": 2000,
            "am5": 1.5,
            "table": "Main",
            "image": "enchanted_grilled_porkchop.gif",
            "r": "Slayer Lv.7"
        },
        "Severed Hand": {
            "locked": false,
            "xpRequired": 1053357,
            "w5": 7,
            "table": "Main",
            "r": "Slayer Lv.7"
        },
        "Shard of the Shredded": {
            "locked": false,
            "xpRequired": 921687,
            "w5": 8,
            "table": "Main",
            "r": "Slayer Lv.7"
        },
        "Warden Heart": {
            "locked": false,
            "xpRequired": 3686750,
            "w5": 2,
            "table": "Main",
            "r": "Slayer Lv.7"
        }
    },
    "Spider": {
        "Brick Red Dye": {
            "dye": true,
            "table": "Handled Separately",
            "locked": false,
            "xpRequired": 75000000,
            "w4": 0.0002,
            "w5": 0.0004,
            "r": "None"
        },
        "Toxic Arrow Poison": {
            "locked": false,
            "xpRequired": 3277,
            "w4": 1800,
            "w5": 1800,
            "am4": 40,
            "am5": 64,
            "table": "Main",
            "r": "None"
        },
        "◆ Bite Rune I": {
            "locked": false,
            "xpRequired": 7657,
            "w4": 833,
            "w5": 833,
            "table": "Extra",
            "r": "None",
            "image": "bite_rune.png"
        },
        "◆ Darkness Within Rune I": {
            "locked": false,
            "xpRequired": 74880,
            "w4": 50,
            "w5": 100,
            "table": "Extra",
            "r": "None",
            "image": "darkness_rune.png"
        },
        "Spider Catalyst": {
            "locked": false,
            "xpRequired": 24250,
            "w4": 75,
            "w5": 25,
            "table": "Main",
            "r": "Slayer Lv.2"
        },
        "Bane of Arthropods VI": {
            "locked": false,
            "xpRequired": 120269,
            "w4": 50,
            "w5": 50,
            "table": "Main",
            "r": "Slayer Lv.4",
            "image": "enchanted_book.gif"
        },
        "Tarantula Catalyst": {
            "locked": false,
            "xpRequired": 117025,
            "w4": 45,
            "w5": 60,
            "table": "Main",
            "r": "Slayer Lv.5"
        },
        "Fly Swatter": {
            "locked": false,
            "xpRequired": 234050,
            "w4": 20,
            "w5": 30,
            "table": "Main",
            "r": "Slayer Lv.5",
            "image": "enchanted_golden_shovel.gif"
        },
        "Vial of Venom": {
            "locked": false,
            "xpRequired": 351075,
            "w4": 10,
            "w5": 20,
            "table": "Main",
            "r": "Slayer Lv.6"
        },
        "Tarantula Talisman": {
            "locked": false,
            "xpRequired": 234050,
            "w4": 20,
            "w5": 30,
            "table": "Main",
            "r": "Slayer Lv.6"
        },
        "Digested Mosquito": {
            "locked": false,
            "xpRequired": 702150,
            "w4": 7,
            "w5": 10,
            "table": "Main",
            "r": "Slayer Lv.7"
        },
        "Tarantula Silk": {
            "locked": false,
            "xpRequired": 3510,
            "w5": 2000,
            "table": "Main",
            "r": "Slayer Lv.6"
        },
        "Shriveled Wasp": {
            "locked": true,
            "xpRequired": 702150,
            "w5": 10,
            "table": "Main",
            "r": "Slayer Lv.7"
        },
        "Ensnared Snail": {
            "locked": true,
            "xpRequired": 1170250,
            "w5": 6,
            "table": "Main",
            "r": "Slayer Lv.7"
        },
        "Primordial Eye": {
            "locked": true,
            "xpRequired": 3510750,
            "w5": 2,
            "table": "Main",
            "r": "Slayer Lv.7"
        }
    },
    "Wolf": {
        "Celeste Dye": {
            "dye": true,
            "table": "Handled Separately",
            "locked": false,
            "xpRequired": 75000000,
            "w4": 0.0002,
            "r": "None"
        },
        "Hamster Wheel": {
            "locked": false,
            "xpRequired": 3000,
            "w4": 2000,
            "table": "Main",
            "r": "None",
            "image": "enchanted_trapdoor.gif"
        },
        "◆ Spirit Rune I": {
            "locked": false,
            "xpRequired": 7917,
            "w4": 833,
            "table": "Extra",
            "r": "Slayer Lv.2",
            "image": "spirit_rune.png"
        },
        "Critical VI": {
            "locked": false,
            "xpRequired": 61634,
            "w4": 100,
            "table": "Main",
            "r": "Slayer Lv.4",
            "image": "enchanted_book.gif"
        },
        "Furball": {
            "locked": false,
            "xpRequired": 30637,
            "w4": 200,
            "table": "Main",
            "r": "Slayer Lv.4"
        },
        "Red Claw Egg": {
            "locked": false,
            "xpRequired": 410900,
            "w4": 15,
            "table": "Main",
            "r": "Slayer Lv.5"
        },
        "◆ Couture Rune I": {
            "locked": false,
            "xpRequired": 219833,
            "w4": 30,
            "table": "Extra",
            "r": "Slayer Lv.6",
            "image": "couture_rune.png"
        },
        "Grizzly Salmon": {
            "locked": false,
            "xpRequired": 880500,
            "w4": 7,
            "table": "Main",
            "r": "Slayer Lv.7"
        },
        "Overflux Capacitor": {
            "locked": false,
            "xpRequired": 1232700,
            "w4": 5,
            "table": "Main",
            "r": "Slayer Lv.7",
            "image": "enchanted_quartz.gif"
        }
    },
    "Enderman": {
        "Byzantium Dye": {
            "dye": true,
            "table": "Handled Separately",
            "locked": false,
            "xpRequired": 75000000,
            "w4": 0.0002,
            "r": "None"
        },
        "Twilight Arrow Poison": {
            "locked": false,
            "xpRequired": 3300,
            "w4": 1800,
            "table": "Main",
            "r": "None"
        },
        "◆ Endersnake Rune I": {
            "locked": false,
            "xpRequired": 9438,
            "w4": 800,
            "table": "Extra",
            "r": "None",
            "image": "endersnake_rune.png"
        },
        "Summoning Eye": {
            "locked": false,
            "xpRequired": 74250,
            "w4": 80,
            "table": "Main",
            "r": "Slayer Lv.1"
        },
        "Mana Steal I": {
            "locked": false,
            "xpRequired": 11183,
            "w4": 600,
            "table": "Main",
            "r": "Slayer Lv.2",
            "image": "enchanted_book.gif"
        },
        "Transmission Tuner": {
            "locked": false,
            "xpRequired": 22366,
            "w4": 300,
            "table": "Main",
            "r": "Slayer Lv.3"
        },
        "Null Atom": {
            "locked": false,
            "xpRequired": 10120,
            "w4": 700,
            "table": "Main",
            "r": "Slayer Lv.4",
            "image": "enchanted_oak_button.gif"
        },
        "Hazmat Enderman": {
            "locked": false,
            "xpRequired": 32202,
            "w4": 220,
            "table": "Main",
            "r": "Slayer Lv.4"
        },
        "Pocket Espresso Machine": {
            "locked": false,
            "xpRequired": 128809,
            "w4": 55,
            "table": "Main",
            "r": "Slayer Lv.4"
        },
        "Smarty Pants I": {
            "locked": false,
            "xpRequired": 28338,
            "w4": 250,
            "table": "Main",
            "r": "Slayer Lv.5",
            "image": "enchanted_book.gif"
        },
        "◆ End Rune I": {
            "locked": false,
            "xpRequired": 75505,
            "w4": 100,
            "table": "Extra",
            "r": "Slayer Lv.5",
            "image": "end_rune.png"
        },
        "Handy Blood Chalice": {
            "locked": false,
            "xpRequired": 283380,
            "w4": 25,
            "table": "Main",
            "r": "Slayer Lv.5"
        },
        "Sinful Dice": {
            "locked": false,
            "xpRequired": 108992,
            "w4": 65,
            "table": "Main",
            "r": "Slayer Lv.6"
        },
        "Exceedingly Rare Ender Artifact Upgrade": {
            "locked": false,
            "xpRequired": 1771125,
            "w4": 4,
            "table": "Main",
            "r": "Slayer Lv.6"
        },
        "Void Conqueror Enderman Skin": {
            "locked": false,
            "xpRequired": 302020,
            "w4": 25,
            "table": "Extra",
            "r": "Slayer Lv.7"
        },
        "Etherwarp Merger": {
            "locked": false,
            "xpRequired": 118075,
            "w4": 60,
            "table": "Main",
            "r": "Slayer Lv.7"
        },
        "◆ Enchant Rune I": {
            "locked": false,
            "xpRequired": 1078642,
            "w4": 7,
            "table": "Extra",
            "r": "Slayer Lv.7",
            "image": "enchant_rune.png"
        },
        "Judgement Core": {
            "locked": false,
            "xpRequired": 1078642,
            "w4": 8,
            "table": "Main",
            "r": "Slayer Lv.7"
        },
        "End Stone Idol": {
            "locked": false,
            "xpRequired": 3542250,
            "w4": 2,
            "table": "Main",
            "r": "Slayer Lv.7"
        }
    },
    "Vampire": {
        "Sangria Dye": {
            "dye": true,
            "table": "Handled Separately",
            "locked": false,
            "xpRequired": 750000,
            "w4": 0.0025,
            "w5": 0.01,
            "r": "None"
        },
        "Quantum Book Bundle": {
            "locked": false,
            "xpRequired": 1687,
            "w4": 20,
            "w5": 20,
            "table": "Main",
            "r": "Slayer Lv.2"
        },
        "◆ Soultwist Rune I": {
            "locked": false,
            "xpRequired": 1912,
            "w4": 20,
            "w5": 20,
            "table": "Extra",
            "r": "Slayer Lv.2",
            "image": "soultwist_rune.png"
        },
        "Bubba Blister": {
            "locked": false,
            "xpRequired": 2250,
            "w4": 15,
            "w5": 15,
            "table": "Main",
            "r": "Slayer Lv.3"
        },
        "Fang-tastic Chocolate Chip": {
            "locked": false,
            "xpRequired": 2250,
            "w4": 15,
            "w5": 15,
            "table": "Main",
            "r": "Slayer Lv.3"
        },
        "Guardian Lucky Block": {
            "locked": false,
            "xpRequired": 3600,
            "w4": 10,
            "w5": 10,
            "table": "Main",
            "r": "Slayer Lv.4"
        },
        "McGrubber's Burger": {
            "locked": false,
            "xpRequired": 18450,
            "w4": 2,
            "w5": 2,
            "table": "Main",
            "r": "Slayer Lv.5",
            "image": "burger.png"
        },
        "Unfanged Vampire Part": {
            "locked": false,
            "xpRequired": 18450,
            "w4": 2,
            "w5": 2,
            "table": "Main",
            "r": "Slayer Lv.5"
        },
        "The One Book Bundle": {
            "locked": false,
            "xpRequired": 12525,
            "w5": 3,
            "table": "Main",
            "r": "Slayer Lv.5"
        }
    },
    "Blaze": {
        "Flame Dye": {
            "dye": true,
            "table": "Handled Separately",
            "locked": false,
            "xpRequired": 75000000,
            "w4": 0.0002,
            "r": "None"
        },
        "Enchanted Blaze Powder": {
            "locked": false,
            "xpRequired": 2351,
            "w4": 2700,
            "am4": 28,
            "table": "Extra",
            "r": "None",
            "image": "enchanted_blaze_powder.gif"
        },
        "◆ Lavatears Rune I": {
            "locked": false,
            "xpRequired": 21660,
            "w4": 450,
            "table": "Extra",
            "r": "None",
            "image": "lavatears_rune.png"
        },
        "Wisp's Ice-Flavored Water I": {
            "locked": false,
            "xpRequired": 14270,
            "w4": 500,
            "am4": 5,
            "table": "Main",
            "r": "None",
            "image": "splash_potion_of_water_breathing.gif"
        },
        "Bundle of Magma Arrows": {
            "locked": false,
            "xpRequired": 4756,
            "w4": 1500,
            "table": "Main",
            "r": "Slayer Lv.1"
        },
        "Mana Disintegrator": {
            "locked": false,
            "xpRequired": 10192,
            "w4": 700,
            "table": "Main",
            "r": "Slayer Lv.2"
        },
        "Scorched Books": {
            "locked": false,
            "xpRequired": 17837,
            "w4": 400,
            "table": "Main",
            "r": "Slayer Lv.2"
        },
        "Kelvin Inverter": {
            "locked": false,
            "xpRequired": 14270,
            "w4": 500,
            "table": "Main",
            "r": "Slayer Lv.3"
        },
        "Gabagool Distillate": {
            "locked": false,
            "xpRequired": 10649,
            "w4": 670,
            "am4": 28,
            "table": "Main",
            "r": "Slayer Lv.3"
        },
        "Scorched Power Crystal": {
            "locked": false,
            "xpRequired": 12558,
            "w4": 600,
            "table": "Main",
            "r": "Slayer Lv.4"
        },
        "Archfiend Dice": {
            "locked": false,
            "xpRequired": 37675,
            "w4": 200,
            "table": "Main",
            "r": "Slayer Lv.4"
        },
        "Fire Aspect III": {
            "locked": false,
            "xpRequired": 32508,
            "w4": 250,
            "table": "Main",
            "r": "Slayer Lv.5",
            "image": "enchanted_book.gif"
        },
        "◆ Fiery Burst Rune I": {
            "locked": false,
            "xpRequired": 243675,
            "w4": 40,
            "table": "Extra",
            "r": "Slayer Lv.5",
            "image": "fiery_burst_rune.png"
        },
        "Flawed Opal Gemstone": {
            "locked": false,
            "xpRequired": 14776,
            "w4": 550,
            "am4": 320,
            "table": "Main",
            "r": "Slayer Lv.5"
        },
        "Duplex I": {
            "locked": false,
            "xpRequired": 23220,
            "w4": 350,
            "table": "Main",
            "r": "Slayer Lv.6",
            "image": "enchanted_book.gif"
        },
        "High Class Archfiend Dice": {
            "locked": false,
            "xpRequired": 194939,
            "w4": 50,
            "table": "Extra",
            "r": "Slayer Lv.7"
        },
        "Wilson's Engineering Plans": {
            "locked": false,
            "xpRequired": 478058,
            "w4": 17,
            "table": "Main",
            "r": "Slayer Lv.7",
            "image": "enchanted_paper.gif"
        },
        "Subzero Inverter": {
            "locked": false,
            "xpRequired": 478058,
            "w4": 17,
            "table": "Main",
            "r": "Slayer Lv.7"
        }
    },
    "slayerWeightSum": {
        "Zombie4Main": 12327,
        "Zombie4Extra": 13180,
        "Zombie5Main": 14527,
        "Zombie5Extra": 15380,
        "Spider4Main": 12027,
        "Spider4Extra": 12910,
        "Spider5Main": 14043,
        "Spider5Extra": 14976,
        "Wolf4Main": 12327,
        "Wolf4Extra": 13190,
        "Vampire4Main": 164,
        "Vampire4Extra": 184,
        "Vampire5Main": 167,
        "Vampire5Extra": 187,
        "Enderman4Main": 14169,
        "Enderman4Extra": 15101,
        "Blaze4Main": 16254,
        "Blaze4Extra": 19494
    },
    "F1": {
        "Rejuvenate I": {
            "locked": false,
            "xpRequired": null
        },
        "Combo I": {
            "locked": false,
            "xpRequired": null
        },
        "No Pain No Gain I": {
            "locked": false,
            "xpRequired": null
        },
        "Necromancer's Brooch": {
            "locked": false,
            "xpRequired": null,
            "skullTexture": "ewogICJ0aW1lc3RhbXAiIDogMTY0MTA0NDU5MDI3MiwKICAicHJvZmlsZUlkIiA6ICI0ZWQ4MjMzNzFhMmU0YmI3YTVlYWJmY2ZmZGE4NDk1NyIsCiAgInByb2ZpbGVOYW1lIiA6ICJGaXJlYnlyZDg4IiwKICAic2lnbmF0dXJlUmVxdWlyZWQiIDogdHJ1ZSwKICAidGV4dHVyZXMiIDogewogICAgIlNLSU4iIDogewogICAgICAidXJsIiA6ICJodHRwOi8vdGV4dHVyZXMubWluZWNyYWZ0Lm5ldC90ZXh0dXJlL2Y1YjZiZWFjNTczNjVjYWY0NmYwMzdmM2QyYTNhNDU3ZjZjYWZlNjQ3NTdiYWYxNGU4OTkzY2QyZGExOGNmZjciCiAgICB9CiAgfQp9"
        },
        "Infinite Quiver VI": {
            "locked": false,
            "xpRequired": null
        },
        "Feather Falling VI": {
            "locked": false,
            "xpRequired": null
        },
        "Hot Potato Book": {
            "locked": false,
            "id": "book",
            "xpRequired": null
        },
        "Balloon Snake": {
            "locked": false,
            "xpRequired": null,
            "skullTexture": "ewogICJ0aW1lc3RhbXAiIDogMTY5MjI5ODI0MDc0MSwKICAicHJvZmlsZUlkIiA6ICI2ZDgwYjVkMjQyMGY0MWZkOTQxMjM4YzA3YzVlYzAxNSIsCiAgInByb2ZpbGVOYW1lIiA6ICJQb05pWW8iLAogICJzaWduYXR1cmVSZXF1aXJlZCIgOiB0cnVlLAogICJ0ZXh0dXJlcyIgOiB7CiAgICAiU0tJTiIgOiB7CiAgICAgICJ1cmwiIDogImh0dHA6Ly90ZXh0dXJlcy5taW5lY3JhZnQubmV0L3RleHR1cmUvOTUzMDg4ZGUzZWRmZDFiMTA5OGQ4ZDhmNTZmNTAwNGE4OTMwNTUxZTA2M2M3Nzg5MWZhMDA3MDNjZjAzMWI5OSIKICAgIH0KICB9Cn0="
        },
        "Bonzo's Mask": {
            "locked": false,
            "xpRequired": null,
            "skullTexture": "eyJ0aW1lc3RhbXAiOjE1ODc5MDgzMDU4MjYsInByb2ZpbGVJZCI6IjJkYzc3YWU3OTQ2MzQ4MDI5NDI4MGM4NDIyNzRiNTY3IiwicHJvZmlsZU5hbWUiOiJzYWR5MDYxMCIsInNpZ25hdHVyZVJlcXVpcmVkIjp0cnVlLCJ0ZXh0dXJlcyI6eyJTS0lOIjp7InVybCI6Imh0dHA6Ly90ZXh0dXJlcy5taW5lY3JhZnQubmV0L3RleHR1cmUvMTI3MTZlY2JmNWI4ZGEwMGIwNWYzMTZlYzZhZjYxZThiZDAyODA1YjIxZWI4ZTQ0MDE1MTQ2OGRjNjU2NTQ5YyJ9fX0="
        },
        "Red Nose": {
            "locked": false,
            "xpRequired": null,
            "skullTexture": "ewogICJ0aW1lc3RhbXAiIDogMTU5MzYxMTA5MzQ5MSwKICAicHJvZmlsZUlkIiA6ICJlNzkzYjJjYTdhMmY0MTI2YTA5ODA5MmQ3Yzk5NDE3YiIsCiAgInByb2ZpbGVOYW1lIiA6ICJUaGVfSG9zdGVyX01hbiIsCiAgInNpZ25hdHVyZVJlcXVpcmVkIiA6IHRydWUsCiAgInRleHR1cmVzIiA6IHsKICAgICJTS0lOIiA6IHsKICAgICAgInVybCIgOiAiaHR0cDovL3RleHR1cmVzLm1pbmVjcmFmdC5uZXQvdGV4dHVyZS82Yjc0OTBiNzY5YzkwYjI5YzRkMDgzNzE1YTc1MmEwNTU4NzhjYzE5NTQzNDUxYWMzODdmODhmNzQ5MzQ1OTA2IgogICAgfQogIH0KfQ=="
        },
        "Fuming Potato Book": {
            "locked": false,
            "id": "book",
            "xpRequired": null
        },
        "Bank I": {
            "locked": false,
            "xpRequired": null
        },
        "Bonzo's Staff": {
            "locked": false,
            "id": "blaze_rod",
            "xpRequired": null
        },
        "Ultimate Jerry I": {
            "locked": false,
            "xpRequired": null
        }
    },
    "F2": {
        "Rejuvenate I": {
            "locked": false,
            "xpRequired": null
        },
        "Ultimate Wise I": {
            "locked": false,
            "xpRequired": null
        },
        "Hot Potato Book": {
            "locked": false,
            "id": "book",
            "xpRequired": null
        },
        "Combo I": {
            "locked": false,
            "xpRequired": null
        },
        "No Pain No Gain I": {
            "locked": false,
            "xpRequired": null
        },
        "Necromancer's Brooch": {
            "locked": false,
            "xpRequired": null,
            "skullTexture": "ewogICJ0aW1lc3RhbXAiIDogMTY0MTA0NDU5MDI3MiwKICAicHJvZmlsZUlkIiA6ICI0ZWQ4MjMzNzFhMmU0YmI3YTVlYWJmY2ZmZGE4NDk1NyIsCiAgInByb2ZpbGVOYW1lIiA6ICJGaXJlYnlyZDg4IiwKICAic2lnbmF0dXJlUmVxdWlyZWQiIDogdHJ1ZSwKICAidGV4dHVyZXMiIDogewogICAgIlNLSU4iIDogewogICAgICAidXJsIiA6ICJodHRwOi8vdGV4dHVyZXMubWluZWNyYWZ0Lm5ldC90ZXh0dXJlL2Y1YjZiZWFjNTczNjVjYWY0NmYwMzdmM2QyYTNhNDU3ZjZjYWZlNjQ3NTdiYWYxNGU4OTkzY2QyZGExOGNmZjciCiAgICB9CiAgfQp9"
        },
        "Adaptive Belt": {
            "locked": false,
            "xpRequired": null,
            "skullTexture": "ewogICJ0aW1lc3RhbXAiIDogMTY5MjI5ODI2MTU3NCwKICAicHJvZmlsZUlkIiA6ICIwOWQ3YmJjNGYxZmU0ZjlkYjRiZmE1MTY2NDA3OTcyYiIsCiAgInByb2ZpbGVOYW1lIiA6ICJlemtkIiwKICAic2lnbmF0dXJlUmVxdWlyZWQiIDogdHJ1ZSwKICAidGV4dHVyZXMiIDogewogICAgIlNLSU4iIDogewogICAgICAidXJsIiA6ICJodHRwOi8vdGV4dHVyZXMubWluZWNyYWZ0Lm5ldC90ZXh0dXJlLzcwYmY2ZDc2ZjJhMDNmMzE5ZmZmZTcyNWY4MmI4MGI5MjUyOTFlZmRhMzZkNGRiMjViYWNkN2VhODZhNjU3YyIKICAgIH0KICB9Cn0="
        },
        "Fuming Potato Book": {
            "locked": false,
            "id": "book",
            "xpRequired": null
        },
        "Recombobulator 3000": {
            "locked": false,
            "xpRequired": null,
            "skullTexture": "ewogICJ0aW1lc3RhbXAiIDogMTcwOTY2NDE2NjkxMSwKICAicHJvZmlsZUlkIiA6ICI5ZWEwMjA0NDZhNGM0ZTQ2ODZiOGU1ZDBiZGU4Y2U1NiIsCiAgInByb2ZpbGVOYW1lIiA6ICJTYW01MTAyMDgiLAogICJzaWduYXR1cmVSZXF1aXJlZCIgOiB0cnVlLAogICJ0ZXh0dXJlcyIgOiB7CiAgICAiU0tJTiIgOiB7CiAgICAgICJ1cmwiIDogImh0dHA6Ly90ZXh0dXJlcy5taW5lY3JhZnQubmV0L3RleHR1cmUvNTdjY2QzNmRjOGY3MmFkY2IxZjhjOGU2MWVlODJjZDk2ZWFkMTQwY2YyYTE2YTEzNjZiZTliNWE4ZTNjYzNmYyIsCiAgICAgICJtZXRhZGF0YSIgOiB7CiAgICAgICAgIm1vZGVsIiA6ICJzbGltIgogICAgICB9CiAgICB9CiAgfQp9"
        },
        "Adaptive Blade": {
            "locked": false,
            "id": "stone_sword",
            "xpRequired": null
        },
        "Bank I": {
            "locked": false,
            "xpRequired": null
        },
        "Red Scarf": {
            "locked": false,
            "xpRequired": null,
            "skullTexture": "ewogICJ0aW1lc3RhbXAiIDogMTY0MTA0NDY0NDAyNSwKICAicHJvZmlsZUlkIiA6ICIyNzZlMDQ2YjI0MDM0M2VkOTk2NmU0OTRlN2U2Y2IzNCIsCiAgInByb2ZpbGVOYW1lIiA6ICJBRFJBTlM3MTAiLAogICJzaWduYXR1cmVSZXF1aXJlZCIgOiB0cnVlLAogICJ0ZXh0dXJlcyIgOiB7CiAgICAiU0tJTiIgOiB7CiAgICAgICJ1cmwiIDogImh0dHA6Ly90ZXh0dXJlcy5taW5lY3JhZnQubmV0L3RleHR1cmUvOTQzMWExZWZlMzMyNjNmYTAwZWZkZjQ3OWNmNDBhMTFjMTMxNmRiMzIzYmM4ZDc4NzNmODk5N2U4ZTJmNzVkOSIKICAgIH0KICB9Cn0="
        }
    },
    "F3": {
        "Last Stand I": {
            "locked": false,
            "xpRequired": null
        },
        "Rejuvenate II": {
            "locked": false,
            "xpRequired": null
        },
        "Ultimate Wise I": {
            "locked": false,
            "xpRequired": null
        },
        "Bank II": {
            "locked": false,
            "xpRequired": null
        },
        "Wisdom I": {
            "locked": false,
            "xpRequired": null
        },
        "Hot Potato Book": {
            "locked": false,
            "id": "book",
            "xpRequired": null
        },
        "Combo I": {
            "locked": false,
            "xpRequired": null
        },
        "No Pain No Gain I": {
            "locked": false,
            "xpRequired": null
        },
        "Recombobulator 3000": {
            "locked": false,
            "xpRequired": null,
            "skullTexture": "ewogICJ0aW1lc3RhbXAiIDogMTcwOTY2NDE2NjkxMSwKICAicHJvZmlsZUlkIiA6ICI5ZWEwMjA0NDZhNGM0ZTQ2ODZiOGU1ZDBiZGU4Y2U1NiIsCiAgInByb2ZpbGVOYW1lIiA6ICJTYW01MTAyMDgiLAogICJzaWduYXR1cmVSZXF1aXJlZCIgOiB0cnVlLAogICJ0ZXh0dXJlcyIgOiB7CiAgICAiU0tJTiIgOiB7CiAgICAgICJ1cmwiIDogImh0dHA6Ly90ZXh0dXJlcy5taW5lY3JhZnQubmV0L3RleHR1cmUvNTdjY2QzNmRjOGY3MmFkY2IxZjhjOGU2MWVlODJjZDk2ZWFkMTQwY2YyYTE2YTEzNjZiZTliNWE4ZTNjYzNmYyIsCiAgICAgICJtZXRhZGF0YSIgOiB7CiAgICAgICAgIm1vZGVsIiA6ICJzbGltIgogICAgICB9CiAgICB9CiAgfQp9"
        },
        "Necromancer's Brooch": {
            "locked": false,
            "xpRequired": null,
            "skullTexture": "ewogICJ0aW1lc3RhbXAiIDogMTY0MTA0NDU5MDI3MiwKICAicHJvZmlsZUlkIiA6ICI0ZWQ4MjMzNzFhMmU0YmI3YTVlYWJmY2ZmZGE4NDk1NyIsCiAgInByb2ZpbGVOYW1lIiA6ICJGaXJlYnlyZDg4IiwKICAic2lnbmF0dXJlUmVxdWlyZWQiIDogdHJ1ZSwKICAidGV4dHVyZXMiIDogewogICAgIlNLSU4iIDogewogICAgICAidXJsIiA6ICJodHRwOi8vdGV4dHVyZXMubWluZWNyYWZ0Lm5ldC90ZXh0dXJlL2Y1YjZiZWFjNTczNjVjYWY0NmYwMzdmM2QyYTNhNDU3ZjZjYWZlNjQ3NTdiYWYxNGU4OTkzY2QyZGExOGNmZjciCiAgICB9CiAgfQp9"
        },
        "Fuming Potato Book": {
            "locked": false,
            "id": "book",
            "xpRequired": null
        },
        "Adaptive Helmet": {
            "locked": false,
            "xpRequired": null,
            "skullTexture": "ewogICJ0aW1lc3RhbXAiIDogMTcyMDAzOTAzMjUzOCwKICAicHJvZmlsZUlkIiA6ICI1MzgyNzM1OGIzOTc0ZmJiOTg0OTY5MWM5Yzg3NTA1YiIsCiAgInByb2ZpbGVOYW1lIiA6ICJPdmVyQmlnYm95MTIzIiwKICAic2lnbmF0dXJlUmVxdWlyZWQiIDogdHJ1ZSwKICAidGV4dHVyZXMiIDogewogICAgIlNLSU4iIDogewogICAgICAidXJsIiA6ICJodHRwOi8vdGV4dHVyZXMubWluZWNyYWZ0Lm5ldC90ZXh0dXJlLzE2ZjBkMzRhYWE3MTQzNzc5ODM3MDFjMWJiZTliM2Y2ZTdiMzBjYjM4NTcxYmMwYTJmZDc1NDFkN2VkYjE2MzciLAogICAgICAibWV0YWRhdGEiIDogewogICAgICAgICJtb2RlbCIgOiAic2xpbSIKICAgICAgfQogICAgfQogIH0KfQ=="
        },
        "Adaptive Boots": {
            "locked": false,
            "id": "leather_boots",
            "xpRequired": null
        },
        "Adaptive Chestplate": {
            "locked": false,
            "id": "leather_chestplate",
            "xpRequired": null
        },
        "Adaptive Leggings": {
            "locked": false,
            "id": "leather_leggings",
            "xpRequired": null
        },
        "Ultimate Jerry II": {
            "locked": false,
            "xpRequired": null
        }
    },
    "F4": {
        "Last Stand I": {
            "locked": false,
            "xpRequired": null
        },
        "Rejuvenate II": {
            "locked": false,
            "xpRequired": null
        },
        "Ultimate Wise I": {
            "locked": false,
            "xpRequired": null
        },
        "Bank II": {
            "locked": false,
            "xpRequired": null
        },
        "Wisdom I": {
            "locked": false,
            "xpRequired": null
        },
        "Hot Potato Book": {
            "locked": false,
            "id": "book",
            "xpRequired": null
        },
        "Combo I": {
            "locked": false,
            "xpRequired": null
        },
        "No Pain No Gain I": {
            "locked": false,
            "xpRequired": null
        },
        "Fuming Potato Book": {
            "locked": false,
            "id": "book",
            "xpRequired": null
        },
        "Spirit Wing": {
            "locked": false,
            "xpRequired": null,
            "skullTexture": "ewogICJ0aW1lc3RhbXAiIDogMTU5NjAzODQyNTM5OSwKICAicHJvZmlsZUlkIiA6ICJjZGM5MzQ0NDAzODM0ZDdkYmRmOWUyMmVjZmM5MzBiZiIsCiAgInByb2ZpbGVOYW1lIiA6ICJSYXdMb2JzdGVycyIsCiAgInNpZ25hdHVyZVJlcXVpcmVkIiA6IHRydWUsCiAgInRleHR1cmVzIiA6IHsKICAgICJTS0lOIiA6IHsKICAgICAgInVybCIgOiAiaHR0cDovL3RleHR1cmVzLm1pbmVjcmFmdC5uZXQvdGV4dHVyZS9lMjlhZDc2YzI0NTk5MTFjMmJiYWNkY2QwYTdiODJlMDgzNTU2N2UzZTUxMzRiMDVhNmY1YWY2NjlkZDg4YjgzIgogICAgfQogIH0KfQ=="
        },
        "Spirit Bone": {
            "locked": false,
            "xpRequired": null,
            "skullTexture": "eyJ0aW1lc3RhbXAiOjE1NzE0OTg0NzUxNTYsInByb2ZpbGVJZCI6ImVkNTNkZDgxNGY5ZDRhM2NiNGViNjUxZGNiYTc3ZTY2IiwicHJvZmlsZU5hbWUiOiJGb3J5eExPTCIsInNpZ25hdHVyZVJlcXVpcmVkIjp0cnVlLCJ0ZXh0dXJlcyI6eyJTS0lOIjp7InVybCI6Imh0dHA6Ly90ZXh0dXJlcy5taW5lY3JhZnQubmV0L3RleHR1cmUvZDg0ODA1MTdhNDQ5N2NmN2NiZjFmYzVlZjhlZWViMTExMTliYTA3MzZkOTNkNTFiYzVlMWU2ZGE5MGU2OTgyNCJ9fX0="
        },
        "Spirit Stone": {
            "locked": false,
            "xpRequired": null,
            "skullTexture": "ewogICJ0aW1lc3RhbXAiIDogMTU5NTAxMjc4ODI0MywKICAicHJvZmlsZUlkIiA6ICI4MmM2MDZjNWM2NTI0Yjc5OGI5MWExMmQzYTYxNjk3NyIsCiAgInByb2ZpbGVOYW1lIiA6ICJOb3ROb3RvcmlvdXNOZW1vIiwKICAic2lnbmF0dXJlUmVxdWlyZWQiIDogdHJ1ZSwKICAidGV4dHVyZXMiIDogewogICAgIlNLSU4iIDogewogICAgICAidXJsIiA6ICJodHRwOi8vdGV4dHVyZXMubWluZWNyYWZ0Lm5ldC90ZXh0dXJlL2RiZmUwOThjNzM2NmZmYWJhYzQ4ZjdkNDY1MDI3MjEyZjZhNzdlZGQ3M2FjYWZjYWQyYzA4NzVmMTFhMDMxYjIiCiAgICB9CiAgfQp9"
        },
        "Rend II": {
            "locked": false,
            "xpRequired": null
        },
        "Spirit Sword": {
            "locked": false,
            "id": "iron_sword",
            "xpRequired": null
        },
        "Spirit Shortbow": {
            "locked": false,
            "id": "bow",
            "xpRequired": null
        },
        "Spirit Boots": {
            "locked": false,
            "id": "leather_boots",
            "xpRequired": null
        },
        "[Lvl 1] Spirit": {
            "locked": false,
            "xpRequired": null,
            "skullTexture": "ewogICJ0aW1lc3RhbXAiIDogMTU5NTg2MjAyNjE5OSwKICAicHJvZmlsZUlkIiA6ICI0ZWQ4MjMzNzFhMmU0YmI3YTVlYWJmY2ZmZGE4NDk1NyIsCiAgInByb2ZpbGVOYW1lIiA6ICJGaXJlYnlyZDg4IiwKICAic2lnbmF0dXJlUmVxdWlyZWQiIDogdHJ1ZSwKICAidGV4dHVyZXMiIDogewogICAgIlNLSU4iIDogewogICAgICAidXJsIiA6ICJodHRwOi8vdGV4dHVyZXMubWluZWNyYWZ0Lm5ldC90ZXh0dXJlLzhkOWNjYzY3MDY3N2QwY2ViYWFkNDA1OGQ2YWFmOWFjZmFiMDlhYmVhNWQ4NjM3OWEwNTk5MDJmMmZlMjI2NTUiCiAgICB9CiAgfQp9"
        },
        "Ultimate Jerry II": {
            "locked": false,
            "xpRequired": null
        }
    },
    "F5": {
        "Rejuvenate III": {
            "locked": false,
            "xpRequired": null
        },
        "Last Stand II": {
            "locked": false,
            "xpRequired": null
        },
        "Ultimate Wise II": {
            "locked": false,
            "xpRequired": null
        },
        "Dark Orb": {
            "locked": false,
            "xpRequired": null,
            "skullTexture": "ewogICJ0aW1lc3RhbXAiIDogMTYyMTA2MTU4ODI0NSwKICAicHJvZmlsZUlkIiA6ICI4MmM2MDZjNWM2NTI0Yjc5OGI5MWExMmQzYTYxNjk3NyIsCiAgInByb2ZpbGVOYW1lIiA6ICJOb3ROb3RvcmlvdXNOZW1vIiwKICAic2lnbmF0dXJlUmVxdWlyZWQiIDogdHJ1ZSwKICAidGV4dHVyZXMiIDogewogICAgIlNLSU4iIDogewogICAgICAidXJsIiA6ICJodHRwOi8vdGV4dHVyZXMubWluZWNyYWZ0Lm5ldC90ZXh0dXJlLzk3YzQwMzZmODBiZjM2MDkxODBjN2M0YTk1Njg4NTNmZDgxNWYxNTRhZDg0MzhiOTJmMzg1MTAxOTgzNWIwNzAiLAogICAgICAibWV0YWRhdGEiIDogewogICAgICAgICJtb2RlbCIgOiAic2xpbSIKICAgICAgfQogICAgfQogIH0KfQ=="
        },
        "Wisdom II": {
            "locked": false,
            "xpRequired": null
        },
        "Fuming Potato Book": {
            "locked": false,
            "id": "book",
            "xpRequired": null
        },
        "Overload I": {
            "locked": false,
            "xpRequired": null
        },
        "Legion I": {
            "locked": false,
            "xpRequired": null
        },
        "Lethality VI": {
            "locked": false,
            "xpRequired": null
        },
        "Combo II": {
            "locked": false,
            "xpRequired": null
        },
        "No Pain No Gain II": {
            "locked": false,
            "xpRequired": null
        },
        "Bank III": {
            "locked": false,
            "xpRequired": null
        },
        "Shadow Assassin Boots": {
            "locked": false,
            "id": "leather_boots",
            "xpRequired": null
        },
        "Shadow Assassin Helmet": {
            "locked": false,
            "xpRequired": null,
            "skullTexture": "ewogICJ0aW1lc3RhbXAiIDogMTYxOTM0NjY3MzMxNCwKICAicHJvZmlsZUlkIiA6ICJiMGQ3MzJmZTAwZjc0MDdlOWU3Zjc0NjMwMWNkOThjYSIsCiAgInByb2ZpbGVOYW1lIiA6ICJPUHBscyIsCiAgInNpZ25hdHVyZVJlcXVpcmVkIiA6IHRydWUsCiAgInRleHR1cmVzIiA6IHsKICAgICJTS0lOIiA6IHsKICAgICAgInVybCIgOiAiaHR0cDovL3RleHR1cmVzLm1pbmVjcmFmdC5uZXQvdGV4dHVyZS9hMWFhMTRkZTljMTU4ZDM1MTM5NDljODVjYWJiOWUzNzg0OGI5ODRlYzNmYjViNDRhMzIxOWY0ZmI1OGEwMGRhIgogICAgfQogIH0KfQ=="
        },
        "Recombobulator 3000": {
            "locked": false,
            "xpRequired": null,
            "skullTexture": "ewogICJ0aW1lc3RhbXAiIDogMTcwOTY2NDE2NjkxMSwKICAicHJvZmlsZUlkIiA6ICI5ZWEwMjA0NDZhNGM0ZTQ2ODZiOGU1ZDBiZGU4Y2U1NiIsCiAgInByb2ZpbGVOYW1lIiA6ICJTYW01MTAyMDgiLAogICJzaWduYXR1cmVSZXF1aXJlZCIgOiB0cnVlLAogICJ0ZXh0dXJlcyIgOiB7CiAgICAiU0tJTiIgOiB7CiAgICAgICJ1cmwiIDogImh0dHA6Ly90ZXh0dXJlcy5taW5lY3JhZnQubmV0L3RleHR1cmUvNTdjY2QzNmRjOGY3MmFkY2IxZjhjOGU2MWVlODJjZDk2ZWFkMTQwY2YyYTE2YTEzNjZiZTliNWE4ZTNjYzNmYyIsCiAgICAgICJtZXRhZGF0YSIgOiB7CiAgICAgICAgIm1vZGVsIiA6ICJzbGltIgogICAgICB9CiAgICB9CiAgfQp9"
        },
        "Shadow Assassin Leggings": {
            "locked": false,
            "id": "leather_leggings",
            "xpRequired": null
        },
        "Shadow Assassin Cloak": {
            "locked": false,
            "xpRequired": null,
            "skullTexture": "ewogICJ0aW1lc3RhbXAiIDogMTY5MjI5ODIwNzA1MywKICAicHJvZmlsZUlkIiA6ICIzZWUxYWRlMzljZDI0ZjFkOWYwODliYjA2ZTkzNTY5YSIsCiAgInByb2ZpbGVOYW1lIiA6ICJSdXNvR01SIiwKICAic2lnbmF0dXJlUmVxdWlyZWQiIDogdHJ1ZSwKICAidGV4dHVyZXMiIDogewogICAgIlNLSU4iIDogewogICAgICAidXJsIiA6ICJodHRwOi8vdGV4dHVyZXMubWluZWNyYWZ0Lm5ldC90ZXh0dXJlL2ZhMjQzMTE0ODU3MmZlZDdiYzFlYWNmMGQyMjlkZGIyMTE1ZDFhMmNhMTgxZDMyM2QzZmNhNTIyNmU1MTZhMWQiCiAgICB9CiAgfQp9"
        },
        "Livid Dagger": {
            "locked": false,
            "id": "iron_sword",
            "xpRequired": null
        },
        "Ultimate Jerry III": {
            "locked": false,
            "xpRequired": null
        },
        "Shadow Assassin Chestplate": {
            "locked": false,
            "id": "leather_chestplate",
            "xpRequired": null
        },
        "Warped Stone": {
            "locked": false,
            "xpRequired": null,
            "skullTexture": "ewogICJ0aW1lc3RhbXAiIDogMTY1MjE0NjU0MzEyMywKICAicHJvZmlsZUlkIiA6ICJjOWRlZTM4MDUzYjg0YzI5YjZlZjA5YjJlMDM5OTc0ZiIsCiAgInByb2ZpbGVOYW1lIiA6ICJTQVJfRGVjZW1iZXI1IiwKICAic2lnbmF0dXJlUmVxdWlyZWQiIDogdHJ1ZSwKICAidGV4dHVyZXMiIDogewogICAgIlNLSU4iIDogewogICAgICAidXJsIiA6ICJodHRwOi8vdGV4dHVyZXMubWluZWNyYWZ0Lm5ldC90ZXh0dXJlLzU0ZDQ4YWM3ZTY1YjkxNDY3OTA0ZjJmNGQxNTQ1NTY3NzZmZmE5Y2QyZDUyNmIxMmEwNDk5YmI1OWNjNjU2YzciLAogICAgICAibWV0YWRhdGEiIDogewogICAgICAgICJtb2RlbCIgOiAic2xpbSIKICAgICAgfQogICAgfQogIH0KfQ=="
        },
        "Last Breath": {
            "locked": false,
            "id": "bow",
            "xpRequired": null
        }
    },
    "F6": {
        "Rejuvenate III": {
            "locked": false,
            "xpRequired": null
        },
        "Last Stand II": {
            "locked": false,
            "xpRequired": null
        },
        "Ultimate Wise II": {
            "locked": false,
            "xpRequired": null
        },
        "Wisdom II": {
            "locked": false,
            "xpRequired": null
        },
        "Fuming Potato Book": {
            "locked": false,
            "id": "book",
            "xpRequired": null
        },
        "Combo II": {
            "locked": false,
            "xpRequired": null
        },
        "No Pain No Gain II": {
            "locked": false,
            "xpRequired": null
        },
        "Bank III": {
            "locked": false,
            "xpRequired": null
        },
        "Swarm I": {
            "locked": false,
            "xpRequired": null
        },
        "Recombobulator 3000": {
            "locked": false,
            "xpRequired": null,
            "skullTexture": "ewogICJ0aW1lc3RhbXAiIDogMTcwOTY2NDE2NjkxMSwKICAicHJvZmlsZUlkIiA6ICI5ZWEwMjA0NDZhNGM0ZTQ2ODZiOGU1ZDBiZGU4Y2U1NiIsCiAgInByb2ZpbGVOYW1lIiA6ICJTYW01MTAyMDgiLAogICJzaWduYXR1cmVSZXF1aXJlZCIgOiB0cnVlLAogICJ0ZXh0dXJlcyIgOiB7CiAgICAiU0tJTiIgOiB7CiAgICAgICJ1cmwiIDogImh0dHA6Ly90ZXh0dXJlcy5taW5lY3JhZnQubmV0L3RleHR1cmUvNTdjY2QzNmRjOGY3MmFkY2IxZjhjOGU2MWVlODJjZDk2ZWFkMTQwY2YyYTE2YTEzNjZiZTliNWE4ZTNjYzNmYyIsCiAgICAgICJtZXRhZGF0YSIgOiB7CiAgICAgICAgIm1vZGVsIiA6ICJzbGltIgogICAgICB9CiAgICB9CiAgfQp9"
        },
        "Necromancer Lord Boots": {
            "locked": false,
            "id": "leather_boots",
            "xpRequired": null
        },
        "Giant Tooth": {
            "locked": false,
            "xpRequired": null,
            "skullTexture": "ewogICJ0aW1lc3RhbXAiIDogMTY0MTA0NTU1NTcyNCwKICAicHJvZmlsZUlkIiA6ICI3NzI3ZDM1NjY5Zjk0MTUxODAyM2Q2MmM2ODE3NTkxOCIsCiAgInByb2ZpbGVOYW1lIiA6ICJsaWJyYXJ5ZnJlYWsiLAogICJzaWduYXR1cmVSZXF1aXJlZCIgOiB0cnVlLAogICJ0ZXh0dXJlcyIgOiB7CiAgICAiU0tJTiIgOiB7CiAgICAgICJ1cmwiIDogImh0dHA6Ly90ZXh0dXJlcy5taW5lY3JhZnQubmV0L3RleHR1cmUvYmEyNjM2YTBmZDQwMzQ1Y2EyOTUxZmRhMDUzNDYwZTY2ZmFiNjNmM2ZjMjE3ODM3MTEzZTIwNDM1N2JiZjgyYiIKICAgIH0KICB9Cn0="
        },
        "Necromancer Lord Helmet": {
            "locked": false,
            "xpRequired": null,
            "skullTexture": "ewogICJ0aW1lc3RhbXAiIDogMTcyMDA0NDAxNDg2MiwKICAicHJvZmlsZUlkIiA6ICJlY2Q0ZTI4NjdkMmE0MTE2OTljYzlkMjMzYmM1YmEyMyIsCiAgInByb2ZpbGVOYW1lIiA6ICJSYXRlZEtub3QiLAogICJzaWduYXR1cmVSZXF1aXJlZCIgOiB0cnVlLAogICJ0ZXh0dXJlcyIgOiB7CiAgICAiU0tJTiIgOiB7CiAgICAgICJ1cmwiIDogImh0dHA6Ly90ZXh0dXJlcy5taW5lY3JhZnQubmV0L3RleHR1cmUvN2RhZGU4YmFlNTY3YTA2NzBmYmViMDI1ZTYzNTA2YTA2ZTQwMTBlZjY2NDRmZjdiNTU2YmRmOTNkMjYwODk1NCIKICAgIH0KICB9Cn0="
        },
        "Sadan's Brooch": {
            "locked": false,
            "xpRequired": null,
            "skullTexture": "ewogICJ0aW1lc3RhbXAiIDogMTYwMTQ4MDAxOTQ1MCwKICAicHJvZmlsZUlkIiA6ICJjZGM5MzQ0NDAzODM0ZDdkYmRmOWUyMmVjZmM5MzBiZiIsCiAgInByb2ZpbGVOYW1lIiA6ICJSYXdMb2JzdGVycyIsCiAgInNpZ25hdHVyZVJlcXVpcmVkIiA6IHRydWUsCiAgInRleHR1cmVzIiA6IHsKICAgICJTS0lOIiA6IHsKICAgICAgInVybCIgOiAiaHR0cDovL3RleHR1cmVzLm1pbmVjcmFmdC5uZXQvdGV4dHVyZS9jYzhiNDdhMWE4ZjEwZDI5NTgzNjVlMTdhZjcyZWEyZTJlOTIyMGZlZmIzZDgwZDhmMzYxMTZhZjcxZWI0YWU3IgogICAgfQogIH0KfQ=="
        },
        "Ultimate Jerry III": {
            "locked": false,
            "xpRequired": null
        },
        "Necromancer Lord Leggings": {
            "locked": false,
            "id": "leather_leggings",
            "xpRequired": null
        },
        "Soulweaver Gloves": {
            "locked": false,
            "xpRequired": null,
            "skullTexture": "ewogICJ0aW1lc3RhbXAiIDogMTY5MjI5ODIyMjY4MywKICAicHJvZmlsZUlkIiA6ICI4NzE3ZGFhNmM3OTU0NzE2YmJlYWQ0MDRkYzg0NDQzZSIsCiAgInByb2ZpbGVOYW1lIiA6ICJTa3VsbDAwMDAiLAogICJzaWduYXR1cmVSZXF1aXJlZCIgOiB0cnVlLAogICJ0ZXh0dXJlcyIgOiB7CiAgICAiU0tJTiIgOiB7CiAgICAgICJ1cmwiIDogImh0dHA6Ly90ZXh0dXJlcy5taW5lY3JhZnQubmV0L3RleHR1cmUvYTUyMjg2NzcyMTJiZTQzZWFhZDIzZDQ3ZWQ4NDNlMTVmYjFlNjgzODQ1OTRjMDliNThiMjNmODI0MjdlNTQ5YSIKICAgIH0KICB9Cn0="
        },
        "Necromancer Sword": {
            "locked": false,
            "id": "iron_sword",
            "xpRequired": null
        },
        "Fel Skull": {
            "locked": false,
            "xpRequired": null,
            "skullTexture": "ewogICJ0aW1lc3RhbXAiIDogMTY5NDQ0NzI4Nzc0NSwKICAicHJvZmlsZUlkIiA6ICJmZDYwZjM2ZjU4NjE0ZjEyYjNjZDQ3YzJkODU1Mjk5YSIsCiAgInByb2ZpbGVOYW1lIiA6ICJSZWFkIiwKICAic2lnbmF0dXJlUmVxdWlyZWQiIDogdHJ1ZSwKICAidGV4dHVyZXMiIDogewogICAgIlNLSU4iIDogewogICAgICAidXJsIiA6ICJodHRwOi8vdGV4dHVyZXMubWluZWNyYWZ0Lm5ldC90ZXh0dXJlLzNlN2Q1OTg0NzAxMTk4YjVmMTdjNWI5MzA3NDgxYzczZjZlY2I2M2ViY2FlZDQxYzFlYTg1Yzk5YzIwNDRjYWUiCiAgICB9CiAgfQp9"
        },
        "Summoning Ring": {
            "locked": false,
            "xpRequired": null,
            "skullTexture": "ewogICJ0aW1lc3RhbXAiIDogMTYzNTcxNzczNjM4NiwKICAicHJvZmlsZUlkIiA6ICIwNjNhMTc2Y2RkMTU0ODRiYjU1MjRhNjQyMGM1YjdhNCIsCiAgInByb2ZpbGVOYW1lIiA6ICJkYXZpcGF0dXJ5IiwKICAic2lnbmF0dXJlUmVxdWlyZWQiIDogdHJ1ZSwKICAidGV4dHVyZXMiIDogewogICAgIlNLSU4iIDogewogICAgICAidXJsIiA6ICJodHRwOi8vdGV4dHVyZXMubWluZWNyYWZ0Lm5ldC90ZXh0dXJlLzc3MGQxNTk5ZWVmZDU2MjFkMTBhYjY5OTYzZDJhOWIxYjBjOWExZTg5OTllYTg4YTU5NzcyNDQ1ZWQyZjAzOTYiCiAgICB9CiAgfQp9"
        },
        "Necromancer Lord Chestplate": {
            "locked": false,
            "id": "leather_chestplate",
            "xpRequired": null
        },
        "Precursor Eye": {
            "locked": false,
            "xpRequired": null,
            "skullTexture": "ewogICJ0aW1lc3RhbXAiIDogMTYwMTQ3OTI0MjkyNCwKICAicHJvZmlsZUlkIiA6ICI1NjY3NWIyMjMyZjA0ZWUwODkxNzllOWM5MjA2Y2ZlOCIsCiAgInByb2ZpbGVOYW1lIiA6ICJUaGVJbmRyYSIsCiAgInNpZ25hdHVyZVJlcXVpcmVkIiA6IHRydWUsCiAgInRleHR1cmVzIiA6IHsKICAgICJTS0lOIiA6IHsKICAgICAgInVybCIgOiAiaHR0cDovL3RleHR1cmVzLm1pbmVjcmFmdC5uZXQvdGV4dHVyZS83MmMwNjgzYjIwMTljYTNkMzk0NzI3M2UzOTRiZmNhMWI0ZDcxYjYxYjY3YjM5NDc0YzJkNmQ3M2E5YjY3NTA4IgogICAgfQogIH0KfQ=="
        }
    },
    "F7": {
        "Precursor Gear": {
            "locked": false,
            "xpRequired": null,
            "skullTexture": "ewogICJ0aW1lc3RhbXAiIDogMTU4OTMyNjI5NDg5NiwKICAicHJvZmlsZUlkIiA6ICJiZWNkZGIyOGEyYzg0OWI0YTliMDkyMmE1ODA1MTQyMCIsCiAgInByb2ZpbGVOYW1lIiA6ICJTdFR2IiwKICAic2lnbmF0dXJlUmVxdWlyZWQiIDogdHJ1ZSwKICAidGV4dHVyZXMiIDogewogICAgIlNLSU4iIDogewogICAgICAidXJsIiA6ICJodHRwOi8vdGV4dHVyZXMubWluZWNyYWZ0Lm5ldC90ZXh0dXJlLzFmZjEwN2UyMGU5NWY1ZjZhYjYxYWU3M2RjNDI1MjNhMTEyZmM0NThjMzMzYTExNDgxMmIzMTNhMmI4ZGQ4YTciLAogICAgICAibWV0YWRhdGEiIDogewogICAgICAgICJtb2RlbCIgOiAic2xpbSIKICAgICAgfQogICAgfQogIH0KfQ=="
        },
        "Combo II": {
            "locked": false,
            "xpRequired": null
        },
        "Rejuvenate III": {
            "locked": false,
            "xpRequired": null
        },
        "Last Stand II": {
            "locked": false,
            "xpRequired": null
        },
        "Infinite Quiver VII": {
            "locked": false,
            "xpRequired": null
        },
        "Soul Eater I": {
            "locked": false,
            "xpRequired": null
        },
        "Hot Potato Book": {
            "locked": false,
            "id": "book",
            "xpRequired": null
        },
        "Ultimate Wise II": {
            "locked": false,
            "xpRequired": null
        },
        "Ultimate Jerry III": {
            "locked": false,
            "xpRequired": null
        },
        "Bank III": {
            "locked": false,
            "xpRequired": null
        },
        "Wisdom II": {
            "locked": false,
            "xpRequired": null
        },
        "Wither Cloak Sword": {
            "locked": false,
            "id": "stone_sword",
            "xpRequired": null
        },
        "Wither Helmet": {
            "locked": false,
            "xpRequired": null,
            "skullTexture": "ewogICJ0aW1lc3RhbXAiIDogMTY4OTY4MzY3MDM4NywKICAicHJvZmlsZUlkIiA6ICJkNzU2OTc4MWUyYjY0OWIyYjVlMjVlYTJhNDZkOGQxOSIsCiAgInByb2ZpbGVOYW1lIiA6ICJEckthcGRvciIsCiAgInNpZ25hdHVyZVJlcXVpcmVkIiA6IHRydWUsCiAgInRleHR1cmVzIiA6IHsKICAgICJTS0lOIiA6IHsKICAgICAgInVybCIgOiAiaHR0cDovL3RleHR1cmVzLm1pbmVjcmFmdC5uZXQvdGV4dHVyZS82OTExMjk0MDk3ODk1ODlhZTFiNDNlMWQ4MjhjMDZmYzlhMjEzYjc4MzQ4YTY4YjczMTNiZGQ0MDFkNzQ4NWNjIiwKICAgICAgIm1ldGFkYXRhIiA6IHsKICAgICAgICAibW9kZWwiIDogInNsaW0iCiAgICAgIH0KICAgIH0KICB9Cn0="
        },
        "Wither Blood": {
            "locked": false,
            "xpRequired": null,
            "skullTexture": "ewogICJ0aW1lc3RhbXAiIDogMTYwNTU0MzQ1NTU3OCwKICAicHJvZmlsZUlkIiA6ICI0ZWQ4MjMzNzFhMmU0YmI3YTVlYWJmY2ZmZGE4NDk1NyIsCiAgInByb2ZpbGVOYW1lIiA6ICJGaXJlYnlyZDg4IiwKICAic2lnbmF0dXJlUmVxdWlyZWQiIDogdHJ1ZSwKICAidGV4dHVyZXMiIDogewogICAgIlNLSU4iIDogewogICAgICAidXJsIiA6ICJodHRwOi8vdGV4dHVyZXMubWluZWNyYWZ0Lm5ldC90ZXh0dXJlL2JmNWQyMGUwNjAwMTc0ZGNiYWI3NzQ1ZDk0NDgzMmZiMjA2M2MyYmQxNDkwYzY1MDU5MDFiMjhiZmFhY2Q4ZTUiCiAgICB9CiAgfQp9"
        },
        "Wither Boots": {
            "locked": false,
            "id": "leather_boots",
            "xpRequired": null
        },
        "Recombobulator 3000": {
            "locked": false,
            "xpRequired": null,
            "skullTexture": "ewogICJ0aW1lc3RhbXAiIDogMTcwOTY2NDE2NjkxMSwKICAicHJvZmlsZUlkIiA6ICI5ZWEwMjA0NDZhNGM0ZTQ2ODZiOGU1ZDBiZGU4Y2U1NiIsCiAgInByb2ZpbGVOYW1lIiA6ICJTYW01MTAyMDgiLAogICJzaWduYXR1cmVSZXF1aXJlZCIgOiB0cnVlLAogICJ0ZXh0dXJlcyIgOiB7CiAgICAiU0tJTiIgOiB7CiAgICAgICJ1cmwiIDogImh0dHA6Ly90ZXh0dXJlcy5taW5lY3JhZnQubmV0L3RleHR1cmUvNTdjY2QzNmRjOGY3MmFkY2IxZjhjOGU2MWVlODJjZDk2ZWFkMTQwY2YyYTE2YTEzNjZiZTliNWE4ZTNjYzNmYyIsCiAgICAgICJtZXRhZGF0YSIgOiB7CiAgICAgICAgIm1vZGVsIiA6ICJzbGltIgogICAgICB9CiAgICB9CiAgfQp9"
        },
        "Fuming Potato Book": {
            "locked": false,
            "id": "book",
            "xpRequired": null
        },
        "Wither Catalyst": {
            "locked": false,
            "xpRequired": null,
            "skullTexture": null
        },
        "No Pain No Gain II": {
            "locked": false,
            "xpRequired": null
        },
        "Wither Leggings": {
            "locked": false,
            "id": "leather_leggings",
            "xpRequired": null
        },
        "Feather Falling VII": {
            "locked": false,
            "xpRequired": null
        },
        "Auto Recombobulator": {
            "locked": false,
            "xpRequired": null,
            "skullTexture": "ewogICJ0aW1lc3RhbXAiIDogMTcwODM3NTk0MTA3NywKICAicHJvZmlsZUlkIiA6ICI2NmRmYzFmNTRlNTU0ZTZmODJjNTA5ZjM1NTJiYTkwZCIsCiAgInByb2ZpbGVOYW1lIiA6ICJadWFyaWciLAogICJzaWduYXR1cmVSZXF1aXJlZCIgOiB0cnVlLAogICJ0ZXh0dXJlcyIgOiB7CiAgICAiU0tJTiIgOiB7CiAgICAgICJ1cmwiIDogImh0dHA6Ly90ZXh0dXJlcy5taW5lY3JhZnQubmV0L3RleHR1cmUvNWRmZjhkYmJhYjE1YmZiYjExZTIzYjFmNTBiMzRlZjU0OGFkOTgzMmMwYmQ3ZjVhMTM3OTFhZGFkMDA1N2UxYiIsCiAgICAgICJtZXRhZGF0YSIgOiB7CiAgICAgICAgIm1vZGVsIiA6ICJzbGltIgogICAgICB9CiAgICB9CiAgfQp9"
        },
        "Wither Chestplate": {
            "locked": false,
            "id": "leather_chestplate",
            "xpRequired": null
        },
        "One For All I": {
            "locked": false,
            "xpRequired": null
        },
        "Shadow Warp": {
            "locked": false,
            "id": "writable_book",
            "xpRequired": null
        },
        "Wither Shield": {
            "locked": false,
            "id": "writable_book",
            "xpRequired": null
        },
        "Implosion": {
            "locked": false,
            "id": "writable_book",
            "xpRequired": null
        },
        "Storm the Fish": {
            "locked": false,
            "xpRequired": null,
            "skullTexture": "ewogICJ0aW1lc3RhbXAiIDogMTcyMDA0MzExMTY1OSwKICAicHJvZmlsZUlkIiA6ICJlNDNiMjBiZTIyNWM0NzhkOTc5ZDJhNDllNjc4MWI1NCIsCiAgInByb2ZpbGVOYW1lIiA6ICJMb3JkS2l3aXgiLAogICJzaWduYXR1cmVSZXF1aXJlZCIgOiB0cnVlLAogICJ0ZXh0dXJlcyIgOiB7CiAgICAiU0tJTiIgOiB7CiAgICAgICJ1cmwiIDogImh0dHA6Ly90ZXh0dXJlcy5taW5lY3JhZnQubmV0L3RleHR1cmUvMTRiMGU1MDQwMDZjYTI4ZDg1M2U0M2ZkY2VjZGJlNzU3YTY0ZWFkMjliYjg2YjVjNDE5OGU1YjcxM2RlNzgxNyIKICAgIH0KICB9Cn0="
        },
        "Maxor the Fish": {
            "locked": false,
            "xpRequired": null,
            "skullTexture": "eyJ0aW1lc3RhbXAiOjE0ODEwNDc1OTIxMzAsInByb2ZpbGVJZCI6IjM5YWY2ODQ0NjgwOTRkMmY4YmE0N2U5MmQwODdiZTE4IiwicHJvZmlsZU5hbWUiOiJNSEZfV2l0aGVyIiwic2lnbmF0dXJlUmVxdWlyZWQiOnRydWUsInRleHR1cmVzIjp7IlNLSU4iOnsidXJsIjoiaHR0cDovL3RleHR1cmVzLm1pbmVjcmFmdC5uZXQvdGV4dHVyZS9jZGY3NGUzMjNlZDQxNDM2OTY1ZjVjNTdkZGYyODE1ZDUzMzJmZTk5OWU2OGZiYjlkNmNmNWM4YmQ0MTM5ZiJ9fX0="
        },
        "Goldor the Fish": {
            "locked": false,
            "xpRequired": null,
            "skullTexture": "eyJ0aW1lc3RhbXAiOjE1NjUwMjk3ODk3NDIsInByb2ZpbGVJZCI6Ijc1MTQ0NDgxOTFlNjQ1NDY4Yzk3MzlhNmUzOTU3YmViIiwicHJvZmlsZU5hbWUiOiJUaGFua3NNb2phbmciLCJzaWduYXR1cmVSZXF1aXJlZCI6dHJ1ZSwidGV4dHVyZXMiOnsiU0tJTiI6eyJ1cmwiOiJodHRwOi8vdGV4dHVyZXMubWluZWNyYWZ0Lm5ldC90ZXh0dXJlLzMwYTViYzcyZjM3NmZhZjg2NWYzZTAxN2Q5MzMwMzM4NGViZmJkZWQ0Y2RmMmE2NDkxYTI2MTdmYmUzMWY2MjUifX19"
        }
    },
    "M1": {
        "Rejuvenate I": {
            "locked": false,
            "xpRequired": null
        },
        "Combo I": {
            "locked": false,
            "xpRequired": null
        },
        "No Pain No Gain I": {
            "locked": false,
            "xpRequired": null
        },
        "Necromancer's Brooch": {
            "locked": false,
            "xpRequired": null,
            "skullTexture": "ewogICJ0aW1lc3RhbXAiIDogMTY0MTA0NDU5MDI3MiwKICAicHJvZmlsZUlkIiA6ICI0ZWQ4MjMzNzFhMmU0YmI3YTVlYWJmY2ZmZGE4NDk1NyIsCiAgInByb2ZpbGVOYW1lIiA6ICJGaXJlYnlyZDg4IiwKICAic2lnbmF0dXJlUmVxdWlyZWQiIDogdHJ1ZSwKICAidGV4dHVyZXMiIDogewogICAgIlNLSU4iIDogewogICAgICAidXJsIiA6ICJodHRwOi8vdGV4dHVyZXMubWluZWNyYWZ0Lm5ldC90ZXh0dXJlL2Y1YjZiZWFjNTczNjVjYWY0NmYwMzdmM2QyYTNhNDU3ZjZjYWZlNjQ3NTdiYWYxNGU4OTkzY2QyZGExOGNmZjciCiAgICB9CiAgfQp9"
        },
        "Infinite Quiver VI": {
            "locked": false,
            "xpRequired": null
        },
        "Feather Falling VI": {
            "locked": false,
            "xpRequired": null
        },
        "Hot Potato Book": {
            "locked": false,
            "id": "book",
            "xpRequired": null
        },
        "Red Nose": {
            "locked": false,
            "xpRequired": null,
            "skullTexture": "ewogICJ0aW1lc3RhbXAiIDogMTU5MzYxMTA5MzQ5MSwKICAicHJvZmlsZUlkIiA6ICJlNzkzYjJjYTdhMmY0MTI2YTA5ODA5MmQ3Yzk5NDE3YiIsCiAgInByb2ZpbGVOYW1lIiA6ICJUaGVfSG9zdGVyX01hbiIsCiAgInNpZ25hdHVyZVJlcXVpcmVkIiA6IHRydWUsCiAgInRleHR1cmVzIiA6IHsKICAgICJTS0lOIiA6IHsKICAgICAgInVybCIgOiAiaHR0cDovL3RleHR1cmVzLm1pbmVjcmFmdC5uZXQvdGV4dHVyZS82Yjc0OTBiNzY5YzkwYjI5YzRkMDgzNzE1YTc1MmEwNTU4NzhjYzE5NTQzNDUxYWMzODdmODhmNzQ5MzQ1OTA2IgogICAgfQogIH0KfQ=="
        },
        "Master Skull - Tier 1": {
            "locked": false,
            "xpRequired": null,
            "skullTexture": "ewogICJ0aW1lc3RhbXAiIDogMTY0NTg2MzUyMjUxMiwKICAicHJvZmlsZUlkIiA6ICJiMjdjMjlkZWZiNWU0OTEyYjFlYmQ5NDVkMmI2NzE0YSIsCiAgInByb2ZpbGVOYW1lIiA6ICJIRUtUMCIsCiAgInNpZ25hdHVyZVJlcXVpcmVkIiA6IHRydWUsCiAgInRleHR1cmVzIiA6IHsKICAgICJTS0lOIiA6IHsKICAgICAgInVybCIgOiAiaHR0cDovL3RleHR1cmVzLm1pbmVjcmFmdC5uZXQvdGV4dHVyZS8yNDZkMGQzZDEwNjkxNjVhNDUyM2E4NTgwNThhMDkwYzcwYjc0Mjk5MjlhYmM4NjkwMDljYjZlYmZjZGU3NTA2IgogICAgfQogIH0KfQ=="
        },
        "Bonzo's Mask": {
            "locked": false,
            "xpRequired": null,
            "skullTexture": "eyJ0aW1lc3RhbXAiOjE1ODc5MDgzMDU4MjYsInByb2ZpbGVJZCI6IjJkYzc3YWU3OTQ2MzQ4MDI5NDI4MGM4NDIyNzRiNTY3IiwicHJvZmlsZU5hbWUiOiJzYWR5MDYxMCIsInNpZ25hdHVyZVJlcXVpcmVkIjp0cnVlLCJ0ZXh0dXJlcyI6eyJTS0lOIjp7InVybCI6Imh0dHA6Ly90ZXh0dXJlcy5taW5lY3JhZnQubmV0L3RleHR1cmUvMTI3MTZlY2JmNWI4ZGEwMGIwNWYzMTZlYzZhZjYxZThiZDAyODA1YjIxZWI4ZTQ0MDE1MTQ2OGRjNjU2NTQ5YyJ9fX0="
        },
        "Balloon Snake": {
            "locked": false,
            "xpRequired": null,
            "skullTexture": "ewogICJ0aW1lc3RhbXAiIDogMTY5MjI5ODI0MDc0MSwKICAicHJvZmlsZUlkIiA6ICI2ZDgwYjVkMjQyMGY0MWZkOTQxMjM4YzA3YzVlYzAxNSIsCiAgInByb2ZpbGVOYW1lIiA6ICJQb05pWW8iLAogICJzaWduYXR1cmVSZXF1aXJlZCIgOiB0cnVlLAogICJ0ZXh0dXJlcyIgOiB7CiAgICAiU0tJTiIgOiB7CiAgICAgICJ1cmwiIDogImh0dHA6Ly90ZXh0dXJlcy5taW5lY3JhZnQubmV0L3RleHR1cmUvOTUzMDg4ZGUzZWRmZDFiMTA5OGQ4ZDhmNTZmNTAwNGE4OTMwNTUxZTA2M2M3Nzg5MWZhMDA3MDNjZjAzMWI5OSIKICAgIH0KICB9Cn0="
        },
        "Fuming Potato Book": {
            "locked": false,
            "id": "book",
            "xpRequired": null
        },
        "Bank I": {
            "locked": false,
            "xpRequired": null
        },
        "Bonzo's Staff": {
            "locked": false,
            "id": "blaze_rod",
            "xpRequired": null
        },
        "Ultimate Jerry I": {
            "locked": false,
            "xpRequired": null
        }
    },
    "M2": {
        "Ultimate Wise I": {
            "locked": false,
            "xpRequired": null
        },
        "Rejuvenate I": {
            "locked": false,
            "xpRequired": null
        },
        "Hot Potato Book": {
            "locked": false,
            "id": "book",
            "xpRequired": null
        },
        "Combo I": {
            "locked": false,
            "xpRequired": null
        },
        "No Pain No Gain I": {
            "locked": false,
            "xpRequired": null
        },
        "Necromancer's Brooch": {
            "locked": false,
            "xpRequired": null,
            "skullTexture": "ewogICJ0aW1lc3RhbXAiIDogMTY0MTA0NDU5MDI3MiwKICAicHJvZmlsZUlkIiA6ICI0ZWQ4MjMzNzFhMmU0YmI3YTVlYWJmY2ZmZGE4NDk1NyIsCiAgInByb2ZpbGVOYW1lIiA6ICJGaXJlYnlyZDg4IiwKICAic2lnbmF0dXJlUmVxdWlyZWQiIDogdHJ1ZSwKICAidGV4dHVyZXMiIDogewogICAgIlNLSU4iIDogewogICAgICAidXJsIiA6ICJodHRwOi8vdGV4dHVyZXMubWluZWNyYWZ0Lm5ldC90ZXh0dXJlL2Y1YjZiZWFjNTczNjVjYWY0NmYwMzdmM2QyYTNhNDU3ZjZjYWZlNjQ3NTdiYWYxNGU4OTkzY2QyZGExOGNmZjciCiAgICB9CiAgfQp9"
        },
        "Recombobulator 3000": {
            "locked": false,
            "xpRequired": null,
            "skullTexture": "ewogICJ0aW1lc3RhbXAiIDogMTcwOTY2NDE2NjkxMSwKICAicHJvZmlsZUlkIiA6ICI5ZWEwMjA0NDZhNGM0ZTQ2ODZiOGU1ZDBiZGU4Y2U1NiIsCiAgInByb2ZpbGVOYW1lIiA6ICJTYW01MTAyMDgiLAogICJzaWduYXR1cmVSZXF1aXJlZCIgOiB0cnVlLAogICJ0ZXh0dXJlcyIgOiB7CiAgICAiU0tJTiIgOiB7CiAgICAgICJ1cmwiIDogImh0dHA6Ly90ZXh0dXJlcy5taW5lY3JhZnQubmV0L3RleHR1cmUvNTdjY2QzNmRjOGY3MmFkY2IxZjhjOGU2MWVlODJjZDk2ZWFkMTQwY2YyYTE2YTEzNjZiZTliNWE4ZTNjYzNmYyIsCiAgICAgICJtZXRhZGF0YSIgOiB7CiAgICAgICAgIm1vZGVsIiA6ICJzbGltIgogICAgICB9CiAgICB9CiAgfQp9"
        },
        "Master Skull - Tier 2": {
            "locked": false,
            "xpRequired": null,
            "skullTexture": "ewogICJ0aW1lc3RhbXAiIDogMTY0NTg2MzUyMjUxMiwKICAicHJvZmlsZUlkIiA6ICJiMjdjMjlkZWZiNWU0OTEyYjFlYmQ5NDVkMmI2NzE0YSIsCiAgInByb2ZpbGVOYW1lIiA6ICJIRUtUMCIsCiAgInNpZ25hdHVyZVJlcXVpcmVkIiA6IHRydWUsCiAgInRleHR1cmVzIiA6IHsKICAgICJTS0lOIiA6IHsKICAgICAgInVybCIgOiAiaHR0cDovL3RleHR1cmVzLm1pbmVjcmFmdC5uZXQvdGV4dHVyZS8yNDZkMGQzZDEwNjkxNjVhNDUyM2E4NTgwNThhMDkwYzcwYjc0Mjk5MjlhYmM4NjkwMDljYjZlYmZjZGU3NTA2IgogICAgfQogIH0KfQ=="
        },
        "Adaptive Belt": {
            "locked": false,
            "xpRequired": null,
            "skullTexture": "ewogICJ0aW1lc3RhbXAiIDogMTY5MjI5ODI2MTU3NCwKICAicHJvZmlsZUlkIiA6ICIwOWQ3YmJjNGYxZmU0ZjlkYjRiZmE1MTY2NDA3OTcyYiIsCiAgInByb2ZpbGVOYW1lIiA6ICJlemtkIiwKICAic2lnbmF0dXJlUmVxdWlyZWQiIDogdHJ1ZSwKICAidGV4dHVyZXMiIDogewogICAgIlNLSU4iIDogewogICAgICAidXJsIiA6ICJodHRwOi8vdGV4dHVyZXMubWluZWNyYWZ0Lm5ldC90ZXh0dXJlLzcwYmY2ZDc2ZjJhMDNmMzE5ZmZmZTcyNWY4MmI4MGI5MjUyOTFlZmRhMzZkNGRiMjViYWNkN2VhODZhNjU3YyIKICAgIH0KICB9Cn0="
        },
        "Fuming Potato Book": {
            "locked": false,
            "id": "book",
            "xpRequired": null
        },
        "Adaptive Blade": {
            "locked": false,
            "id": "stone_sword",
            "xpRequired": null
        },
        "Bank I": {
            "locked": false,
            "xpRequired": null
        },
        "Red Scarf": {
            "locked": false,
            "xpRequired": null,
            "skullTexture": "ewogICJ0aW1lc3RhbXAiIDogMTY0MTA0NDY0NDAyNSwKICAicHJvZmlsZUlkIiA6ICIyNzZlMDQ2YjI0MDM0M2VkOTk2NmU0OTRlN2U2Y2IzNCIsCiAgInByb2ZpbGVOYW1lIiA6ICJBRFJBTlM3MTAiLAogICJzaWduYXR1cmVSZXF1aXJlZCIgOiB0cnVlLAogICJ0ZXh0dXJlcyIgOiB7CiAgICAiU0tJTiIgOiB7CiAgICAgICJ1cmwiIDogImh0dHA6Ly90ZXh0dXJlcy5taW5lY3JhZnQubmV0L3RleHR1cmUvOTQzMWExZWZlMzMyNjNmYTAwZWZkZjQ3OWNmNDBhMTFjMTMxNmRiMzIzYmM4ZDc4NzNmODk5N2U4ZTJmNzVkOSIKICAgIH0KICB9Cn0="
        }
    },
    "M3": {
        "Last Stand I": {
            "locked": false,
            "xpRequired": null
        },
        "Rejuvenate II": {
            "locked": false,
            "xpRequired": null
        },
        "Ultimate Wise I": {
            "locked": false,
            "xpRequired": null
        },
        "Bank II": {
            "locked": false,
            "xpRequired": null
        },
        "Wisdom I": {
            "locked": false,
            "xpRequired": null
        },
        "Hot Potato Book": {
            "locked": false,
            "id": "book",
            "xpRequired": null
        },
        "Combo I": {
            "locked": false,
            "xpRequired": null
        },
        "No Pain No Gain I": {
            "locked": false,
            "xpRequired": null
        },
        "Recombobulator 3000": {
            "locked": false,
            "xpRequired": null,
            "skullTexture": "ewogICJ0aW1lc3RhbXAiIDogMTcwOTY2NDE2NjkxMSwKICAicHJvZmlsZUlkIiA6ICI5ZWEwMjA0NDZhNGM0ZTQ2ODZiOGU1ZDBiZGU4Y2U1NiIsCiAgInByb2ZpbGVOYW1lIiA6ICJTYW01MTAyMDgiLAogICJzaWduYXR1cmVSZXF1aXJlZCIgOiB0cnVlLAogICJ0ZXh0dXJlcyIgOiB7CiAgICAiU0tJTiIgOiB7CiAgICAgICJ1cmwiIDogImh0dHA6Ly90ZXh0dXJlcy5taW5lY3JhZnQubmV0L3RleHR1cmUvNTdjY2QzNmRjOGY3MmFkY2IxZjhjOGU2MWVlODJjZDk2ZWFkMTQwY2YyYTE2YTEzNjZiZTliNWE4ZTNjYzNmYyIsCiAgICAgICJtZXRhZGF0YSIgOiB7CiAgICAgICAgIm1vZGVsIiA6ICJzbGltIgogICAgICB9CiAgICB9CiAgfQp9"
        },
        "Master Skull - Tier 3": {
            "locked": false,
            "xpRequired": null,
            "skullTexture": "ewogICJ0aW1lc3RhbXAiIDogMTY0NTg2MzU2Mzg5NywKICAicHJvZmlsZUlkIiA6ICI3NTE0NDQ4MTkxZTY0NTQ2OGM5NzM5YTZlMzk1N2JlYiIsCiAgInByb2ZpbGVOYW1lIiA6ICJUaGFua3NNb2phbmciLAogICJzaWduYXR1cmVSZXF1aXJlZCIgOiB0cnVlLAogICJ0ZXh0dXJlcyIgOiB7CiAgICAiU0tJTiIgOiB7CiAgICAgICJ1cmwiIDogImh0dHA6Ly90ZXh0dXJlcy5taW5lY3JhZnQubmV0L3RleHR1cmUvYmExNTNhZmVkYTFmODBjYjM4MmI1Y2MzMTcxNzUxMDJhMWQ5ZmJkMWQ2YzI2YzkyNTQzMzk3OWE2MzU2NTAxNCIKICAgIH0KICB9Cn0="
        },
        "Necromancer's Brooch": {
            "locked": false,
            "xpRequired": null,
            "skullTexture": "ewogICJ0aW1lc3RhbXAiIDogMTY0MTA0NDU5MDI3MiwKICAicHJvZmlsZUlkIiA6ICI0ZWQ4MjMzNzFhMmU0YmI3YTVlYWJmY2ZmZGE4NDk1NyIsCiAgInByb2ZpbGVOYW1lIiA6ICJGaXJlYnlyZDg4IiwKICAic2lnbmF0dXJlUmVxdWlyZWQiIDogdHJ1ZSwKICAidGV4dHVyZXMiIDogewogICAgIlNLSU4iIDogewogICAgICAidXJsIiA6ICJodHRwOi8vdGV4dHVyZXMubWluZWNyYWZ0Lm5ldC90ZXh0dXJlL2Y1YjZiZWFjNTczNjVjYWY0NmYwMzdmM2QyYTNhNDU3ZjZjYWZlNjQ3NTdiYWYxNGU4OTkzY2QyZGExOGNmZjciCiAgICB9CiAgfQp9"
        },
        "Fuming Potato Book": {
            "locked": false,
            "id": "book",
            "xpRequired": null
        },
        "First Master Star": {
            "locked": false,
            "xpRequired": null,
            "skullTexture": "ewogICJ0aW1lc3RhbXAiIDogMTY0NTgwMjU4MDE1OSwKICAicHJvZmlsZUlkIiA6ICJmZDYwZjM2ZjU4NjE0ZjEyYjNjZDQ3YzJkODU1Mjk5YSIsCiAgInByb2ZpbGVOYW1lIiA6ICJSZWFkIiwKICAic2lnbmF0dXJlUmVxdWlyZWQiIDogdHJ1ZSwKICAidGV4dHVyZXMiIDogewogICAgIlNLSU4iIDogewogICAgICAidXJsIiA6ICJodHRwOi8vdGV4dHVyZXMubWluZWNyYWZ0Lm5ldC90ZXh0dXJlLzYxMzY3MjQ3NDVjOGM5YWJjNzVjZGYyMjA1ZjJjZDFkMzNlNmJmZWZhNDE1Zjk5NWJlNzY5MjI5MTIxNjllYzkiCiAgICB9CiAgfQp9"
        },
        "Adaptive Helmet": {
            "locked": false,
            "xpRequired": null,
            "skullTexture": "ewogICJ0aW1lc3RhbXAiIDogMTcyMDAzOTAzMjUzOCwKICAicHJvZmlsZUlkIiA6ICI1MzgyNzM1OGIzOTc0ZmJiOTg0OTY5MWM5Yzg3NTA1YiIsCiAgInByb2ZpbGVOYW1lIiA6ICJPdmVyQmlnYm95MTIzIiwKICAic2lnbmF0dXJlUmVxdWlyZWQiIDogdHJ1ZSwKICAidGV4dHVyZXMiIDogewogICAgIlNLSU4iIDogewogICAgICAidXJsIiA6ICJodHRwOi8vdGV4dHVyZXMubWluZWNyYWZ0Lm5ldC90ZXh0dXJlLzE2ZjBkMzRhYWE3MTQzNzc5ODM3MDFjMWJiZTliM2Y2ZTdiMzBjYjM4NTcxYmMwYTJmZDc1NDFkN2VkYjE2MzciLAogICAgICAibWV0YWRhdGEiIDogewogICAgICAgICJtb2RlbCIgOiAic2xpbSIKICAgICAgfQogICAgfQogIH0KfQ=="
        },
        "Adaptive Boots": {
            "locked": false,
            "id": "leather_boots",
            "xpRequired": null
        },
        "Adaptive Chestplate": {
            "locked": false,
            "id": "leather_chestplate",
            "xpRequired": null
        },
        "Adaptive Leggings": {
            "locked": false,
            "id": "leather_leggings",
            "xpRequired": null
        },
        "Ultimate Jerry II": {
            "locked": false,
            "xpRequired": null
        }
    },
    "M4": {
        "Last Stand I": {
            "locked": false,
            "xpRequired": null
        },
        "Rejuvenate II": {
            "locked": false,
            "xpRequired": null
        },
        "Ultimate Wise I": {
            "locked": false,
            "xpRequired": null
        },
        "Bank II": {
            "locked": false,
            "xpRequired": null
        },
        "Wisdom I": {
            "locked": false,
            "xpRequired": null
        },
        "Hot Potato Book": {
            "locked": false,
            "id": "book",
            "xpRequired": null
        },
        "Combo I": {
            "locked": false,
            "xpRequired": null
        },
        "No Pain No Gain I": {
            "locked": false,
            "xpRequired": null
        },
        "Recombobulator 3000": {
            "locked": false,
            "xpRequired": null,
            "skullTexture": "ewogICJ0aW1lc3RhbXAiIDogMTcwOTY2NDE2NjkxMSwKICAicHJvZmlsZUlkIiA6ICI5ZWEwMjA0NDZhNGM0ZTQ2ODZiOGU1ZDBiZGU4Y2U1NiIsCiAgInByb2ZpbGVOYW1lIiA6ICJTYW01MTAyMDgiLAogICJzaWduYXR1cmVSZXF1aXJlZCIgOiB0cnVlLAogICJ0ZXh0dXJlcyIgOiB7CiAgICAiU0tJTiIgOiB7CiAgICAgICJ1cmwiIDogImh0dHA6Ly90ZXh0dXJlcy5taW5lY3JhZnQubmV0L3RleHR1cmUvNTdjY2QzNmRjOGY3MmFkY2IxZjhjOGU2MWVlODJjZDk2ZWFkMTQwY2YyYTE2YTEzNjZiZTliNWE4ZTNjYzNmYyIsCiAgICAgICJtZXRhZGF0YSIgOiB7CiAgICAgICAgIm1vZGVsIiA6ICJzbGltIgogICAgICB9CiAgICB9CiAgfQp9"
        },
        "Master Skull - Tier 3": {
            "locked": false,
            "xpRequired": null,
            "skullTexture": "ewogICJ0aW1lc3RhbXAiIDogMTY0NTg2MzU2Mzg5NywKICAicHJvZmlsZUlkIiA6ICI3NTE0NDQ4MTkxZTY0NTQ2OGM5NzM5YTZlMzk1N2JlYiIsCiAgInByb2ZpbGVOYW1lIiA6ICJUaGFua3NNb2phbmciLAogICJzaWduYXR1cmVSZXF1aXJlZCIgOiB0cnVlLAogICJ0ZXh0dXJlcyIgOiB7CiAgICAiU0tJTiIgOiB7CiAgICAgICJ1cmwiIDogImh0dHA6Ly90ZXh0dXJlcy5taW5lY3JhZnQubmV0L3RleHR1cmUvYmExNTNhZmVkYTFmODBjYjM4MmI1Y2MzMTcxNzUxMDJhMWQ5ZmJkMWQ2YzI2YzkyNTQzMzk3OWE2MzU2NTAxNCIKICAgIH0KICB9Cn0="
        },
        "Fuming Potato Book": {
            "locked": false,
            "id": "book",
            "xpRequired": null
        },
        "Spirit Wing": {
            "locked": false,
            "xpRequired": null,
            "skullTexture": "ewogICJ0aW1lc3RhbXAiIDogMTU5NjAzODQyNTM5OSwKICAicHJvZmlsZUlkIiA6ICJjZGM5MzQ0NDAzODM0ZDdkYmRmOWUyMmVjZmM5MzBiZiIsCiAgInByb2ZpbGVOYW1lIiA6ICJSYXdMb2JzdGVycyIsCiAgInNpZ25hdHVyZVJlcXVpcmVkIiA6IHRydWUsCiAgInRleHR1cmVzIiA6IHsKICAgICJTS0lOIiA6IHsKICAgICAgInVybCIgOiAiaHR0cDovL3RleHR1cmVzLm1pbmVjcmFmdC5uZXQvdGV4dHVyZS9lMjlhZDc2YzI0NTk5MTFjMmJiYWNkY2QwYTdiODJlMDgzNTU2N2UzZTUxMzRiMDVhNmY1YWY2NjlkZDg4YjgzIgogICAgfQogIH0KfQ=="
        },
        "Spirit Bone": {
            "locked": false,
            "xpRequired": null,
            "skullTexture": "eyJ0aW1lc3RhbXAiOjE1NzE0OTg0NzUxNTYsInByb2ZpbGVJZCI6ImVkNTNkZDgxNGY5ZDRhM2NiNGViNjUxZGNiYTc3ZTY2IiwicHJvZmlsZU5hbWUiOiJGb3J5eExPTCIsInNpZ25hdHVyZVJlcXVpcmVkIjp0cnVlLCJ0ZXh0dXJlcyI6eyJTS0lOIjp7InVybCI6Imh0dHA6Ly90ZXh0dXJlcy5taW5lY3JhZnQubmV0L3RleHR1cmUvZDg0ODA1MTdhNDQ5N2NmN2NiZjFmYzVlZjhlZWViMTExMTliYTA3MzZkOTNkNTFiYzVlMWU2ZGE5MGU2OTgyNCJ9fX0="
        },
        "Spirit Stone": {
            "locked": false,
            "xpRequired": null,
            "skullTexture": "ewogICJ0aW1lc3RhbXAiIDogMTU5NTAxMjc4ODI0MywKICAicHJvZmlsZUlkIiA6ICI4MmM2MDZjNWM2NTI0Yjc5OGI5MWExMmQzYTYxNjk3NyIsCiAgInByb2ZpbGVOYW1lIiA6ICJOb3ROb3RvcmlvdXNOZW1vIiwKICAic2lnbmF0dXJlUmVxdWlyZWQiIDogdHJ1ZSwKICAidGV4dHVyZXMiIDogewogICAgIlNLSU4iIDogewogICAgICAidXJsIiA6ICJodHRwOi8vdGV4dHVyZXMubWluZWNyYWZ0Lm5ldC90ZXh0dXJlL2RiZmUwOThjNzM2NmZmYWJhYzQ4ZjdkNDY1MDI3MjEyZjZhNzdlZGQ3M2FjYWZjYWQyYzA4NzVmMTFhMDMxYjIiCiAgICB9CiAgfQp9"
        },
        "Rend II": {
            "locked": false,
            "xpRequired": null
        },
        "Spirit Sword": {
            "locked": false,
            "id": "iron_sword",
            "xpRequired": null
        },
        "Spirit Shortbow": {
            "locked": false,
            "id": "bow",
            "xpRequired": null
        },
        "Spirit Boots": {
            "locked": false,
            "id": "leather_boots",
            "xpRequired": null
        },
        "[Lvl 1] Spirit": {
            "locked": false,
            "xpRequired": null,
            "skullTexture": "ewogICJ0aW1lc3RhbXAiIDogMTU5NTg2MjAyNjE5OSwKICAicHJvZmlsZUlkIiA6ICI0ZWQ4MjMzNzFhMmU0YmI3YTVlYWJmY2ZmZGE4NDk1NyIsCiAgInByb2ZpbGVOYW1lIiA6ICJGaXJlYnlyZDg4IiwKICAic2lnbmF0dXJlUmVxdWlyZWQiIDogdHJ1ZSwKICAidGV4dHVyZXMiIDogewogICAgIlNLSU4iIDogewogICAgICAidXJsIiA6ICJodHRwOi8vdGV4dHVyZXMubWluZWNyYWZ0Lm5ldC90ZXh0dXJlLzhkOWNjYzY3MDY3N2QwY2ViYWFkNDA1OGQ2YWFmOWFjZmFiMDlhYmVhNWQ4NjM3OWEwNTk5MDJmMmZlMjI2NTUiCiAgICB9CiAgfQp9"
        },
        "Ultimate Jerry II": {
            "locked": false,
            "xpRequired": null
        }
    },
    "M5": {
        "Rejuvenate III": {
            "locked": false,
            "xpRequired": null
        },
        "Last Stand II": {
            "locked": false,
            "xpRequired": null
        },
        "Dark Orb": {
            "locked": false,
            "xpRequired": null,
            "skullTexture": "ewogICJ0aW1lc3RhbXAiIDogMTYyMTA2MTU4ODI0NSwKICAicHJvZmlsZUlkIiA6ICI4MmM2MDZjNWM2NTI0Yjc5OGI5MWExMmQzYTYxNjk3NyIsCiAgInByb2ZpbGVOYW1lIiA6ICJOb3ROb3RvcmlvdXNOZW1vIiwKICAic2lnbmF0dXJlUmVxdWlyZWQiIDogdHJ1ZSwKICAidGV4dHVyZXMiIDogewogICAgIlNLSU4iIDogewogICAgICAidXJsIiA6ICJodHRwOi8vdGV4dHVyZXMubWluZWNyYWZ0Lm5ldC90ZXh0dXJlLzk3YzQwMzZmODBiZjM2MDkxODBjN2M0YTk1Njg4NTNmZDgxNWYxNTRhZDg0MzhiOTJmMzg1MTAxOTgzNWIwNzAiLAogICAgICAibWV0YWRhdGEiIDogewogICAgICAgICJtb2RlbCIgOiAic2xpbSIKICAgICAgfQogICAgfQogIH0KfQ=="
        },
        "Ultimate Wise II": {
            "locked": false,
            "xpRequired": null
        },
        "Fuming Potato Book": {
            "locked": false,
            "id": "book",
            "xpRequired": null
        },
        "Overload I": {
            "locked": false,
            "xpRequired": null
        },
        "Legion I": {
            "locked": false,
            "xpRequired": null
        },
        "Lethality VI": {
            "locked": false,
            "xpRequired": null
        },
        "Shadow Assassin Boots": {
            "locked": false,
            "id": "leather_boots",
            "xpRequired": null
        },
        "Combo II": {
            "locked": false,
            "xpRequired": null
        },
        "No Pain No Gain II": {
            "locked": false,
            "xpRequired": null
        },
        "Wisdom II": {
            "locked": false,
            "xpRequired": null
        },
        "Shadow Assassin Helmet": {
            "locked": false,
            "xpRequired": null,
            "skullTexture": "ewogICJ0aW1lc3RhbXAiIDogMTYxOTM0NjY3MzMxNCwKICAicHJvZmlsZUlkIiA6ICJiMGQ3MzJmZTAwZjc0MDdlOWU3Zjc0NjMwMWNkOThjYSIsCiAgInByb2ZpbGVOYW1lIiA6ICJPUHBscyIsCiAgInNpZ25hdHVyZVJlcXVpcmVkIiA6IHRydWUsCiAgInRleHR1cmVzIiA6IHsKICAgICJTS0lOIiA6IHsKICAgICAgInVybCIgOiAiaHR0cDovL3RleHR1cmVzLm1pbmVjcmFmdC5uZXQvdGV4dHVyZS9hMWFhMTRkZTljMTU4ZDM1MTM5NDljODVjYWJiOWUzNzg0OGI5ODRlYzNmYjViNDRhMzIxOWY0ZmI1OGEwMGRhIgogICAgfQogIH0KfQ=="
        },
        "Bank III": {
            "locked": false,
            "xpRequired": null
        },
        "Recombobulator 3000": {
            "locked": false,
            "xpRequired": null,
            "skullTexture": "ewogICJ0aW1lc3RhbXAiIDogMTcwOTY2NDE2NjkxMSwKICAicHJvZmlsZUlkIiA6ICI5ZWEwMjA0NDZhNGM0ZTQ2ODZiOGU1ZDBiZGU4Y2U1NiIsCiAgInByb2ZpbGVOYW1lIiA6ICJTYW01MTAyMDgiLAogICJzaWduYXR1cmVSZXF1aXJlZCIgOiB0cnVlLAogICJ0ZXh0dXJlcyIgOiB7CiAgICAiU0tJTiIgOiB7CiAgICAgICJ1cmwiIDogImh0dHA6Ly90ZXh0dXJlcy5taW5lY3JhZnQubmV0L3RleHR1cmUvNTdjY2QzNmRjOGY3MmFkY2IxZjhjOGU2MWVlODJjZDk2ZWFkMTQwY2YyYTE2YTEzNjZiZTliNWE4ZTNjYzNmYyIsCiAgICAgICJtZXRhZGF0YSIgOiB7CiAgICAgICAgIm1vZGVsIiA6ICJzbGltIgogICAgICB9CiAgICB9CiAgfQp9"
        },
        "Shadow Assassin Leggings": {
            "locked": false,
            "id": "leather_leggings",
            "xpRequired": null
        },
        "Shadow Assassin Cloak": {
            "locked": false,
            "xpRequired": null,
            "skullTexture": "ewogICJ0aW1lc3RhbXAiIDogMTY5MjI5ODIwNzA1MywKICAicHJvZmlsZUlkIiA6ICIzZWUxYWRlMzljZDI0ZjFkOWYwODliYjA2ZTkzNTY5YSIsCiAgInByb2ZpbGVOYW1lIiA6ICJSdXNvR01SIiwKICAic2lnbmF0dXJlUmVxdWlyZWQiIDogdHJ1ZSwKICAidGV4dHVyZXMiIDogewogICAgIlNLSU4iIDogewogICAgICAidXJsIiA6ICJodHRwOi8vdGV4dHVyZXMubWluZWNyYWZ0Lm5ldC90ZXh0dXJlL2ZhMjQzMTE0ODU3MmZlZDdiYzFlYWNmMGQyMjlkZGIyMTE1ZDFhMmNhMTgxZDMyM2QzZmNhNTIyNmU1MTZhMWQiCiAgICB9CiAgfQp9"
        },
        "Master Skull - Tier 4": {
            "locked": false,
            "xpRequired": null,
            "skullTexture": "ewogICJ0aW1lc3RhbXAiIDogMTY0NTg2MzU2Mzg5NywKICAicHJvZmlsZUlkIiA6ICI3NTE0NDQ4MTkxZTY0NTQ2OGM5NzM5YTZlMzk1N2JlYiIsCiAgInByb2ZpbGVOYW1lIiA6ICJUaGFua3NNb2phbmciLAogICJzaWduYXR1cmVSZXF1aXJlZCIgOiB0cnVlLAogICJ0ZXh0dXJlcyIgOiB7CiAgICAiU0tJTiIgOiB7CiAgICAgICJ1cmwiIDogImh0dHA6Ly90ZXh0dXJlcy5taW5lY3JhZnQubmV0L3RleHR1cmUvYmExNTNhZmVkYTFmODBjYjM4MmI1Y2MzMTcxNzUxMDJhMWQ5ZmJkMWQ2YzI2YzkyNTQzMzk3OWE2MzU2NTAxNCIKICAgIH0KICB9Cn0="
        },
        "Livid Dagger": {
            "locked": false,
            "id": "iron_sword",
            "xpRequired": null
        },
        "Ultimate Jerry III": {
            "locked": false,
            "xpRequired": null
        },
        "Shadow Assassin Chestplate": {
            "locked": false,
            "id": "leather_chestplate",
            "xpRequired": null
        },
        "Warped Stone": {
            "locked": false,
            "xpRequired": null,
            "skullTexture": "ewogICJ0aW1lc3RhbXAiIDogMTY1MjE0NjU0MzEyMywKICAicHJvZmlsZUlkIiA6ICJjOWRlZTM4MDUzYjg0YzI5YjZlZjA5YjJlMDM5OTc0ZiIsCiAgInByb2ZpbGVOYW1lIiA6ICJTQVJfRGVjZW1iZXI1IiwKICAic2lnbmF0dXJlUmVxdWlyZWQiIDogdHJ1ZSwKICAidGV4dHVyZXMiIDogewogICAgIlNLSU4iIDogewogICAgICAidXJsIiA6ICJodHRwOi8vdGV4dHVyZXMubWluZWNyYWZ0Lm5ldC90ZXh0dXJlLzU0ZDQ4YWM3ZTY1YjkxNDY3OTA0ZjJmNGQxNTQ1NTY3NzZmZmE5Y2QyZDUyNmIxMmEwNDk5YmI1OWNjNjU2YzciLAogICAgICAibWV0YWRhdGEiIDogewogICAgICAgICJtb2RlbCIgOiAic2xpbSIKICAgICAgfQogICAgfQogIH0KfQ=="
        },
        "Shadow Fury": {
            "locked": false,
            "id": "diamond_sword",
            "xpRequired": null
        },
        "Last Breath": {
            "locked": false,
            "id": "bow",
            "xpRequired": null
        },
        "Livid Dye": {
            "dye": true,
            "locked": false,
            "xpRequired": null,
            "skullTexture": "ewogICJ0aW1lc3RhbXAiIDogMTc0MTE2MTE4OTA0OSwKICAicHJvZmlsZUlkIiA6ICIwMzA5NGIxMzM1ZjY0M2RlOGQxM2MzN2MzYTliOTQxYSIsCiAgInByb2ZpbGVOYW1lIiA6ICJDb2FzdGVyRnJlYWtERSIsCiAgInNpZ25hdHVyZVJlcXVpcmVkIiA6IHRydWUsCiAgInRleHR1cmVzIiA6IHsKICAgICJTS0lOIiA6IHsKICAgICAgInVybCIgOiAiaHR0cDovL3RleHR1cmVzLm1pbmVjcmFmdC5uZXQvdGV4dHVyZS84OGIwMjE0MTg5YjVhZjhlNzM1YzlkMjJlYmNiZjZlMjk3YTY1MGU4N2VlNTNhOTI3MGZkNzI0YzdiMzI4ZmZhIiwKICAgICAgIm1ldGFkYXRhIiA6IHsKICAgICAgICAibW9kZWwiIDogInNsaW0iCiAgICAgIH0KICAgIH0KICB9Cn0="
        }
    },
    "M6": {
        "Rejuvenate III": {
            "locked": false,
            "xpRequired": null
        },
        "Last Stand II": {
            "locked": false,
            "xpRequired": null
        },
        "Ultimate Wise II": {
            "locked": false,
            "xpRequired": null
        },
        "Wisdom II": {
            "locked": false,
            "xpRequired": null
        },
        "Fuming Potato Book": {
            "locked": false,
            "id": "book",
            "xpRequired": null
        },
        "Combo II": {
            "locked": false,
            "xpRequired": null
        },
        "No Pain No Gain II": {
            "locked": false,
            "xpRequired": null
        },
        "Bank III": {
            "locked": false,
            "xpRequired": null
        },
        "Swarm I": {
            "locked": false,
            "xpRequired": null
        },
        "Recombobulator 3000": {
            "locked": false,
            "xpRequired": null,
            "skullTexture": "ewogICJ0aW1lc3RhbXAiIDogMTcwOTY2NDE2NjkxMSwKICAicHJvZmlsZUlkIiA6ICI5ZWEwMjA0NDZhNGM0ZTQ2ODZiOGU1ZDBiZGU4Y2U1NiIsCiAgInByb2ZpbGVOYW1lIiA6ICJTYW01MTAyMDgiLAogICJzaWduYXR1cmVSZXF1aXJlZCIgOiB0cnVlLAogICJ0ZXh0dXJlcyIgOiB7CiAgICAiU0tJTiIgOiB7CiAgICAgICJ1cmwiIDogImh0dHA6Ly90ZXh0dXJlcy5taW5lY3JhZnQubmV0L3RleHR1cmUvNTdjY2QzNmRjOGY3MmFkY2IxZjhjOGU2MWVlODJjZDk2ZWFkMTQwY2YyYTE2YTEzNjZiZTliNWE4ZTNjYzNmYyIsCiAgICAgICJtZXRhZGF0YSIgOiB7CiAgICAgICAgIm1vZGVsIiA6ICJzbGltIgogICAgICB9CiAgICB9CiAgfQp9"
        },
        "Necromancer Lord Boots": {
            "locked": false,
            "id": "leather_boots",
            "xpRequired": null
        },
        "Giant Tooth": {
            "locked": false,
            "xpRequired": null,
            "skullTexture": "ewogICJ0aW1lc3RhbXAiIDogMTY0MTA0NTU1NTcyNCwKICAicHJvZmlsZUlkIiA6ICI3NzI3ZDM1NjY5Zjk0MTUxODAyM2Q2MmM2ODE3NTkxOCIsCiAgInByb2ZpbGVOYW1lIiA6ICJsaWJyYXJ5ZnJlYWsiLAogICJzaWduYXR1cmVSZXF1aXJlZCIgOiB0cnVlLAogICJ0ZXh0dXJlcyIgOiB7CiAgICAiU0tJTiIgOiB7CiAgICAgICJ1cmwiIDogImh0dHA6Ly90ZXh0dXJlcy5taW5lY3JhZnQubmV0L3RleHR1cmUvYmEyNjM2YTBmZDQwMzQ1Y2EyOTUxZmRhMDUzNDYwZTY2ZmFiNjNmM2ZjMjE3ODM3MTEzZTIwNDM1N2JiZjgyYiIKICAgIH0KICB9Cn0="
        },
        "Necromancer Lord Helmet": {
            "locked": false,
            "xpRequired": null,
            "skullTexture": "ewogICJ0aW1lc3RhbXAiIDogMTcyMDA0NDAxNDg2MiwKICAicHJvZmlsZUlkIiA6ICJlY2Q0ZTI4NjdkMmE0MTE2OTljYzlkMjMzYmM1YmEyMyIsCiAgInByb2ZpbGVOYW1lIiA6ICJSYXRlZEtub3QiLAogICJzaWduYXR1cmVSZXF1aXJlZCIgOiB0cnVlLAogICJ0ZXh0dXJlcyIgOiB7CiAgICAiU0tJTiIgOiB7CiAgICAgICJ1cmwiIDogImh0dHA6Ly90ZXh0dXJlcy5taW5lY3JhZnQubmV0L3RleHR1cmUvN2RhZGU4YmFlNTY3YTA2NzBmYmViMDI1ZTYzNTA2YTA2ZTQwMTBlZjY2NDRmZjdiNTU2YmRmOTNkMjYwODk1NCIKICAgIH0KICB9Cn0="
        },
        "Sadan's Brooch": {
            "locked": false,
            "xpRequired": null,
            "skullTexture": "ewogICJ0aW1lc3RhbXAiIDogMTYwMTQ4MDAxOTQ1MCwKICAicHJvZmlsZUlkIiA6ICJjZGM5MzQ0NDAzODM0ZDdkYmRmOWUyMmVjZmM5MzBiZiIsCiAgInByb2ZpbGVOYW1lIiA6ICJSYXdMb2JzdGVycyIsCiAgInNpZ25hdHVyZVJlcXVpcmVkIiA6IHRydWUsCiAgInRleHR1cmVzIiA6IHsKICAgICJTS0lOIiA6IHsKICAgICAgInVybCIgOiAiaHR0cDovL3RleHR1cmVzLm1pbmVjcmFmdC5uZXQvdGV4dHVyZS9jYzhiNDdhMWE4ZjEwZDI5NTgzNjVlMTdhZjcyZWEyZTJlOTIyMGZlZmIzZDgwZDhmMzYxMTZhZjcxZWI0YWU3IgogICAgfQogIH0KfQ=="
        },
        "Ultimate Jerry III": {
            "locked": false,
            "xpRequired": null
        },
        "Necromancer Lord Leggings": {
            "locked": false,
            "id": "leather_leggings",
            "xpRequired": null
        },
        "Soulweaver Gloves": {
            "locked": false,
            "xpRequired": null,
            "skullTexture": "ewogICJ0aW1lc3RhbXAiIDogMTY5MjI5ODIyMjY4MywKICAicHJvZmlsZUlkIiA6ICI4NzE3ZGFhNmM3OTU0NzE2YmJlYWQ0MDRkYzg0NDQzZSIsCiAgInByb2ZpbGVOYW1lIiA6ICJTa3VsbDAwMDAiLAogICJzaWduYXR1cmVSZXF1aXJlZCIgOiB0cnVlLAogICJ0ZXh0dXJlcyIgOiB7CiAgICAiU0tJTiIgOiB7CiAgICAgICJ1cmwiIDogImh0dHA6Ly90ZXh0dXJlcy5taW5lY3JhZnQubmV0L3RleHR1cmUvYTUyMjg2NzcyMTJiZTQzZWFhZDIzZDQ3ZWQ4NDNlMTVmYjFlNjgzODQ1OTRjMDliNThiMjNmODI0MjdlNTQ5YSIKICAgIH0KICB9Cn0="
        },
        "Necromancer Sword": {
            "locked": false,
            "id": "iron_sword",
            "xpRequired": null
        },
        "Fel Skull": {
            "locked": false,
            "xpRequired": null,
            "skullTexture": "ewogICJ0aW1lc3RhbXAiIDogMTY5NDQ0NzI4Nzc0NSwKICAicHJvZmlsZUlkIiA6ICJmZDYwZjM2ZjU4NjE0ZjEyYjNjZDQ3YzJkODU1Mjk5YSIsCiAgInByb2ZpbGVOYW1lIiA6ICJSZWFkIiwKICAic2lnbmF0dXJlUmVxdWlyZWQiIDogdHJ1ZSwKICAidGV4dHVyZXMiIDogewogICAgIlNLSU4iIDogewogICAgICAidXJsIiA6ICJodHRwOi8vdGV4dHVyZXMubWluZWNyYWZ0Lm5ldC90ZXh0dXJlLzNlN2Q1OTg0NzAxMTk4YjVmMTdjNWI5MzA3NDgxYzczZjZlY2I2M2ViY2FlZDQxYzFlYTg1Yzk5YzIwNDRjYWUiCiAgICB9CiAgfQp9"
        },
        "Summoning Ring": {
            "locked": false,
            "xpRequired": null,
            "skullTexture": "ewogICJ0aW1lc3RhbXAiIDogMTYzNTcxNzczNjM4NiwKICAicHJvZmlsZUlkIiA6ICIwNjNhMTc2Y2RkMTU0ODRiYjU1MjRhNjQyMGM1YjdhNCIsCiAgInByb2ZpbGVOYW1lIiA6ICJkYXZpcGF0dXJ5IiwKICAic2lnbmF0dXJlUmVxdWlyZWQiIDogdHJ1ZSwKICAidGV4dHVyZXMiIDogewogICAgIlNLSU4iIDogewogICAgICAidXJsIiA6ICJodHRwOi8vdGV4dHVyZXMubWluZWNyYWZ0Lm5ldC90ZXh0dXJlLzc3MGQxNTk5ZWVmZDU2MjFkMTBhYjY5OTYzZDJhOWIxYjBjOWExZTg5OTllYTg4YTU5NzcyNDQ1ZWQyZjAzOTYiCiAgICB9CiAgfQp9"
        },
        "Master Skull - Tier 4": {
            "locked": false,
            "xpRequired": null,
            "skullTexture": "ewogICJ0aW1lc3RhbXAiIDogMTY0NTg2MzU2Mzg5NywKICAicHJvZmlsZUlkIiA6ICI3NTE0NDQ4MTkxZTY0NTQ2OGM5NzM5YTZlMzk1N2JlYiIsCiAgInByb2ZpbGVOYW1lIiA6ICJUaGFua3NNb2phbmciLAogICJzaWduYXR1cmVSZXF1aXJlZCIgOiB0cnVlLAogICJ0ZXh0dXJlcyIgOiB7CiAgICAiU0tJTiIgOiB7CiAgICAgICJ1cmwiIDogImh0dHA6Ly90ZXh0dXJlcy5taW5lY3JhZnQubmV0L3RleHR1cmUvYmExNTNhZmVkYTFmODBjYjM4MmI1Y2MzMTcxNzUxMDJhMWQ5ZmJkMWQ2YzI2YzkyNTQzMzk3OWE2MzU2NTAxNCIKICAgIH0KICB9Cn0="
        },
        "Necromancer Lord Chestplate": {
            "locked": false,
            "id": "leather_chestplate",
            "xpRequired": null
        },
        "Giant's Sword": {
            "locked": false,
            "id": "iron_sword",
            "xpRequired": null
        },
        "Precursor Eye": {
            "locked": false,
            "xpRequired": null,
            "skullTexture": "ewogICJ0aW1lc3RhbXAiIDogMTYwMTQ3OTI0MjkyNCwKICAicHJvZmlsZUlkIiA6ICI1NjY3NWIyMjMyZjA0ZWUwODkxNzllOWM5MjA2Y2ZlOCIsCiAgInByb2ZpbGVOYW1lIiA6ICJUaGVJbmRyYSIsCiAgInNpZ25hdHVyZVJlcXVpcmVkIiA6IHRydWUsCiAgInRleHR1cmVzIiA6IHsKICAgICJTS0lOIiA6IHsKICAgICAgInVybCIgOiAiaHR0cDovL3RleHR1cmVzLm1pbmVjcmFmdC5uZXQvdGV4dHVyZS83MmMwNjgzYjIwMTljYTNkMzk0NzI3M2UzOTRiZmNhMWI0ZDcxYjYxYjY3YjM5NDc0YzJkNmQ3M2E5YjY3NTA4IgogICAgfQogIH0KfQ=="
        }
    },
    "M7": {
        "Precursor Gear": {
            "locked": false,
            "xpRequired": null,
            "skullTexture": "ewogICJ0aW1lc3RhbXAiIDogMTU4OTMyNjI5NDg5NiwKICAicHJvZmlsZUlkIiA6ICJiZWNkZGIyOGEyYzg0OWI0YTliMDkyMmE1ODA1MTQyMCIsCiAgInByb2ZpbGVOYW1lIiA6ICJTdFR2IiwKICAic2lnbmF0dXJlUmVxdWlyZWQiIDogdHJ1ZSwKICAidGV4dHVyZXMiIDogewogICAgIlNLSU4iIDogewogICAgICAidXJsIiA6ICJodHRwOi8vdGV4dHVyZXMubWluZWNyYWZ0Lm5ldC90ZXh0dXJlLzFmZjEwN2UyMGU5NWY1ZjZhYjYxYWU3M2RjNDI1MjNhMTEyZmM0NThjMzMzYTExNDgxMmIzMTNhMmI4ZGQ4YTciLAogICAgICAibWV0YWRhdGEiIDogewogICAgICAgICJtb2RlbCIgOiAic2xpbSIKICAgICAgfQogICAgfQogIH0KfQ=="
        },
        "Combo II": {
            "locked": false,
            "xpRequired": null
        },
        "Rejuvenate III": {
            "locked": false,
            "xpRequired": null
        },
        "Last Stand II": {
            "locked": false,
            "xpRequired": null
        },
        "Infinite Quiver VII": {
            "locked": false,
            "xpRequired": null
        },
        "Soul Eater I": {
            "locked": false,
            "xpRequired": null
        },
        "Hot Potato Book": {
            "locked": false,
            "id": "book",
            "xpRequired": null
        },
        "Ultimate Wise II": {
            "locked": false,
            "xpRequired": null
        },
        "Ultimate Jerry III": {
            "locked": false,
            "xpRequired": null
        },
        "Recombobulator 3000": {
            "locked": false,
            "xpRequired": null,
            "skullTexture": "ewogICJ0aW1lc3RhbXAiIDogMTcwOTY2NDE2NjkxMSwKICAicHJvZmlsZUlkIiA6ICI5ZWEwMjA0NDZhNGM0ZTQ2ODZiOGU1ZDBiZGU4Y2U1NiIsCiAgInByb2ZpbGVOYW1lIiA6ICJTYW01MTAyMDgiLAogICJzaWduYXR1cmVSZXF1aXJlZCIgOiB0cnVlLAogICJ0ZXh0dXJlcyIgOiB7CiAgICAiU0tJTiIgOiB7CiAgICAgICJ1cmwiIDogImh0dHA6Ly90ZXh0dXJlcy5taW5lY3JhZnQubmV0L3RleHR1cmUvNTdjY2QzNmRjOGY3MmFkY2IxZjhjOGU2MWVlODJjZDk2ZWFkMTQwY2YyYTE2YTEzNjZiZTliNWE4ZTNjYzNmYyIsCiAgICAgICJtZXRhZGF0YSIgOiB7CiAgICAgICAgIm1vZGVsIiA6ICJzbGltIgogICAgICB9CiAgICB9CiAgfQp9"
        },
        "Bank III": {
            "locked": false,
            "xpRequired": null
        },
        "Wisdom II": {
            "locked": false,
            "xpRequired": null
        },
        "Wither Cloak Sword": {
            "locked": false,
            "id": "stone_sword",
            "xpRequired": null
        },
        "Wither Helmet": {
            "locked": false,
            "xpRequired": null,
            "skullTexture": "ewogICJ0aW1lc3RhbXAiIDogMTY4OTY4MzY3MDM4NywKICAicHJvZmlsZUlkIiA6ICJkNzU2OTc4MWUyYjY0OWIyYjVlMjVlYTJhNDZkOGQxOSIsCiAgInByb2ZpbGVOYW1lIiA6ICJEckthcGRvciIsCiAgInNpZ25hdHVyZVJlcXVpcmVkIiA6IHRydWUsCiAgInRleHR1cmVzIiA6IHsKICAgICJTS0lOIiA6IHsKICAgICAgInVybCIgOiAiaHR0cDovL3RleHR1cmVzLm1pbmVjcmFmdC5uZXQvdGV4dHVyZS82OTExMjk0MDk3ODk1ODlhZTFiNDNlMWQ4MjhjMDZmYzlhMjEzYjc4MzQ4YTY4YjczMTNiZGQ0MDFkNzQ4NWNjIiwKICAgICAgIm1ldGFkYXRhIiA6IHsKICAgICAgICAibW9kZWwiIDogInNsaW0iCiAgICAgIH0KICAgIH0KICB9Cn0="
        },
        "Wither Blood": {
            "locked": false,
            "xpRequired": null,
            "skullTexture": "ewogICJ0aW1lc3RhbXAiIDogMTYwNTU0MzQ1NTU3OCwKICAicHJvZmlsZUlkIiA6ICI0ZWQ4MjMzNzFhMmU0YmI3YTVlYWJmY2ZmZGE4NDk1NyIsCiAgInByb2ZpbGVOYW1lIiA6ICJGaXJlYnlyZDg4IiwKICAic2lnbmF0dXJlUmVxdWlyZWQiIDogdHJ1ZSwKICAidGV4dHVyZXMiIDogewogICAgIlNLSU4iIDogewogICAgICAidXJsIiA6ICJodHRwOi8vdGV4dHVyZXMubWluZWNyYWZ0Lm5ldC90ZXh0dXJlL2JmNWQyMGUwNjAwMTc0ZGNiYWI3NzQ1ZDk0NDgzMmZiMjA2M2MyYmQxNDkwYzY1MDU5MDFiMjhiZmFhY2Q4ZTUiCiAgICB9CiAgfQp9"
        },
        "Wither Boots": {
            "locked": false,
            "id": "leather_boots",
            "xpRequired": null
        },
        "Fuming Potato Book": {
            "locked": false,
            "id": "book",
            "xpRequired": null
        },
        "Wither Catalyst": {
            "locked": false,
            "xpRequired": null,
            "skullTexture": null
        },
        "No Pain No Gain II": {
            "locked": false,
            "xpRequired": null
        },
        "Wither Leggings": {
            "locked": false,
            "id": "leather_leggings",
            "xpRequired": null
        },
        "Feather Falling VII": {
            "locked": false,
            "xpRequired": null
        },
        "Auto Recombobulator": {
            "locked": false,
            "xpRequired": null,
            "skullTexture": "ewogICJ0aW1lc3RhbXAiIDogMTcwODM3NTk0MTA3NywKICAicHJvZmlsZUlkIiA6ICI2NmRmYzFmNTRlNTU0ZTZmODJjNTA5ZjM1NTJiYTkwZCIsCiAgInByb2ZpbGVOYW1lIiA6ICJadWFyaWciLAogICJzaWduYXR1cmVSZXF1aXJlZCIgOiB0cnVlLAogICJ0ZXh0dXJlcyIgOiB7CiAgICAiU0tJTiIgOiB7CiAgICAgICJ1cmwiIDogImh0dHA6Ly90ZXh0dXJlcy5taW5lY3JhZnQubmV0L3RleHR1cmUvNWRmZjhkYmJhYjE1YmZiYjExZTIzYjFmNTBiMzRlZjU0OGFkOTgzMmMwYmQ3ZjVhMTM3OTFhZGFkMDA1N2UxYiIsCiAgICAgICJtZXRhZGF0YSIgOiB7CiAgICAgICAgIm1vZGVsIiA6ICJzbGltIgogICAgICB9CiAgICB9CiAgfQp9"
        },
        "Wither Chestplate": {
            "locked": false,
            "id": "leather_chestplate",
            "xpRequired": null
        },
        "One For All I": {
            "locked": false,
            "xpRequired": null
        },
        "Fifth Master Star": {
            "locked": false,
            "xpRequired": null,
            "skullTexture": "ewogICJ0aW1lc3RhbXAiIDogMTY0NTgwMjUyNDkxMywKICAicHJvZmlsZUlkIiA6ICJkZTE0MGFmM2NmMjM0ZmM0OTJiZTE3M2Y2NjA3MzViYiIsCiAgInByb2ZpbGVOYW1lIiA6ICJTUlRlYW0iLAogICJzaWduYXR1cmVSZXF1aXJlZCIgOiB0cnVlLAogICJ0ZXh0dXJlcyIgOiB7CiAgICAiU0tJTiIgOiB7CiAgICAgICJ1cmwiIDogImh0dHA6Ly90ZXh0dXJlcy5taW5lY3JhZnQubmV0L3RleHR1cmUvNzFjODA0MjUyN2Y4MWM4ZTI5M2UyODEwMTEzNDg5ZjQzOTRjYzZlZmUxNWQxYWZhYzQzMTU3MWM3M2I2MmRjNCIKICAgIH0KICB9Cn0="
        },
        "Shadow Warp": {
            "locked": false,
            "id": "writable_book",
            "xpRequired": null
        },
        "Wither Shield": {
            "locked": false,
            "id": "writable_book",
            "xpRequired": null
        },
        "Implosion": {
            "locked": false,
            "id": "writable_book",
            "xpRequired": null
        },
        "Master Skull - Tier 5": {
            "locked": false,
            "xpRequired": null,
            "skullTexture": "ewogICJ0aW1lc3RhbXAiIDogMTY0NTg2MzU5NDY5MCwKICAicHJvZmlsZUlkIiA6ICI1YjY2YzNkZWZhYTI0NWMzYTcwNjM3OTA3NTQ0Yjg3MCIsCiAgInByb2ZpbGVOYW1lIiA6ICJSZWFuX1JhaWNvMDgxNiIsCiAgInNpZ25hdHVyZVJlcXVpcmVkIiA6IHRydWUsCiAgInRleHR1cmVzIiA6IHsKICAgICJTS0lOIiA6IHsKICAgICAgInVybCIgOiAiaHR0cDovL3RleHR1cmVzLm1pbmVjcmFmdC5uZXQvdGV4dHVyZS85MTBmOWYxMDg1ZDQwNzE0MWViNzc2MTdhNGFiZGFhYTA4ZDhhZjMzYjk2MDIwMGZlOGMxMjZjMWQxNDQ1NjgyIgogICAgfQogIH0KfQ=="
        },
        "Thunderlord VII": {
            "locked": false,
            "xpRequired": null
        },
        "Dark Claymore": {
            "locked": false,
            "id": "stone_sword",
            "xpRequired": null
        },
        "Storm the Fish": {
            "locked": false,
            "xpRequired": null,
            "skullTexture": "ewogICJ0aW1lc3RhbXAiIDogMTcyMDA0MzExMTY1OSwKICAicHJvZmlsZUlkIiA6ICJlNDNiMjBiZTIyNWM0NzhkOTc5ZDJhNDllNjc4MWI1NCIsCiAgInByb2ZpbGVOYW1lIiA6ICJMb3JkS2l3aXgiLAogICJzaWduYXR1cmVSZXF1aXJlZCIgOiB0cnVlLAogICJ0ZXh0dXJlcyIgOiB7CiAgICAiU0tJTiIgOiB7CiAgICAgICJ1cmwiIDogImh0dHA6Ly90ZXh0dXJlcy5taW5lY3JhZnQubmV0L3RleHR1cmUvMTRiMGU1MDQwMDZjYTI4ZDg1M2U0M2ZkY2VjZGJlNzU3YTY0ZWFkMjliYjg2YjVjNDE5OGU1YjcxM2RlNzgxNyIKICAgIH0KICB9Cn0="
        },
        "Maxor the Fish": {
            "locked": false,
            "xpRequired": null,
            "skullTexture": "eyJ0aW1lc3RhbXAiOjE0ODEwNDc1OTIxMzAsInByb2ZpbGVJZCI6IjM5YWY2ODQ0NjgwOTRkMmY4YmE0N2U5MmQwODdiZTE4IiwicHJvZmlsZU5hbWUiOiJNSEZfV2l0aGVyIiwic2lnbmF0dXJlUmVxdWlyZWQiOnRydWUsInRleHR1cmVzIjp7IlNLSU4iOnsidXJsIjoiaHR0cDovL3RleHR1cmVzLm1pbmVjcmFmdC5uZXQvdGV4dHVyZS9jZGY3NGUzMjNlZDQxNDM2OTY1ZjVjNTdkZGYyODE1ZDUzMzJmZTk5OWU2OGZiYjlkNmNmNWM4YmQ0MTM5ZiJ9fX0="
        },
        "Goldor the Fish": {
            "locked": false,
            "xpRequired": null,
            "skullTexture": "eyJ0aW1lc3RhbXAiOjE1NjUwMjk3ODk3NDIsInByb2ZpbGVJZCI6Ijc1MTQ0NDgxOTFlNjQ1NDY4Yzk3MzlhNmUzOTU3YmViIiwicHJvZmlsZU5hbWUiOiJUaGFua3NNb2phbmciLCJzaWduYXR1cmVSZXF1aXJlZCI6dHJ1ZSwidGV4dHVyZXMiOnsiU0tJTiI6eyJ1cmwiOiJodHRwOi8vdGV4dHVyZXMubWluZWNyYWZ0Lm5ldC90ZXh0dXJlLzMwYTViYzcyZjM3NmZhZjg2NWYzZTAxN2Q5MzMwMzM4NGViZmJkZWQ0Y2RmMmE2NDkxYTI2MTdmYmUzMWY2MjUifX19"
        },
        "Necron Dye": {
            "dye": true,
            "locked": false,
            "xpRequired": null,
            "skullTexture": "ewogICJ0aW1lc3RhbXAiIDogMTc0MTE2MTI3ODI0OSwKICAicHJvZmlsZUlkIiA6ICJmZDJlZDMzMzI0Mjk0ZThmOWVlZGNiN2RhMWJiNzlkZSIsCiAgInByb2ZpbGVOYW1lIiA6ICJkcmFtYWdnIiwKICAic2lnbmF0dXJlUmVxdWlyZWQiIDogdHJ1ZSwKICAidGV4dHVyZXMiIDogewogICAgIlNLSU4iIDogewogICAgICAidXJsIiA6ICJodHRwOi8vdGV4dHVyZXMubWluZWNyYWZ0Lm5ldC90ZXh0dXJlLzM3NzBmNmNjYWY4ODYxZGEzYzg4MTI4MjVhZmFlYzVhOTVjNWYzMzZmNzI4YTI2ZjEzNWEyNTk0YjQ4NzU0MDIiLAogICAgICAibWV0YWRhdGEiIDogewogICAgICAgICJtb2RlbCIgOiAic2xpbSIKICAgICAgfQogICAgfQogIH0KfQ=="
        }
    },
    "Nucleus Runs": {
        "Pickonimbus 2000": {
            "locked": false,
            "xpRequired": 4000,
            "image": "enchanted_diamond_pickaxe.gif",
            "w": 10000
        },
        "Prehistoric Egg": {
            "locked": false,
            "xpRequired": 8000,
            "w": 5000
        },
        "Divan Fragment": {
            "locked": false,
            "xpRequired": 8000,
            "w": 6000
        },
        "Jasper Crystal": {
            "locked": false,
            "xpRequired": 10000,
            "w": 2500
        },
        "Lapidary I": {
            "locked": false,
            "xpRequired": 10000,
            "image": "enchanted_book.gif",
            "w": 4000
        },
        "Helix Fossil": {
            "locked": false,
            "xpRequired": 10000,
            "w": 4000
        },
        "Ruby Crystal": {
            "locked": false,
            "xpRequired": 10000,
            "w": 2500
        },
        "Dwarven O's Gemstone Grahams": {
            "locked": false,
            "xpRequired": 20000,
            "w": 1450
        },
        "Jaderald": {
            "locked": false,
            "xpRequired": 20000,
            "w": 1450
        },
        "Fortune IV": {
            "locked": false,
            "xpRequired": 35000,
            "image": "enchanted_book.gif",
            "w": 700
        },
        "Gemstone Mixture": {
            "locked": false,
            "xpRequired": 35000,
            "w": 700
        },
        "Precious Pearl": {
            "locked": false,
            "xpRequired": 50000,
            "w": 500
        },
        "Claw Fossil": {
            "locked": false,
            "xpRequired": 50000,
            "w": 500
        },
        "Recall Potion": {
            "locked": false,
            "xpRequired": 100000,
            "w": 250
        },
        "Quick Claw": {
            "locked": false,
            "xpRequired": 450000,
            "w": 50
        },
        "Divan's Alloy": {
            "locked": false,
            "xpRequired": 1000000,
            "w": 17
        },
        "Jade Dye": {
            "dye": true,
            "locked": false,
            "xpRequired": 5000000
        }
    }
}
